Workbook

Sheet Dashboard
A1: Adani Ports and Special Economic Zone Ltd - Dashboard
A2: Every figure links into the model: change an input or the scenario switch and this page follows
A4: The call | B4: Value | D4: INR Cr | E4: Mar-26 | F4: Mar-27E | G4: Mar-28E
A5: Rating | B5: =DCF!B60 -> SELL | D5: Revenue | E5: ='Income Statement'!K6 -> 38735.77 | F5: ='Income Statement'!L6 -> 47021.351 | G5: ='Income Statement'!M6 -> 53143.531
A6: Target price (INR) | B6: =DCF!B56 -> 575 | D6: EBITDA | E6: ='Income Statement'!K10 -> 22868.19 | F6: ='Income Statement'!L10 -> 27507.49 | G6: ='Income Statement'!M10 -> 30823.248
A7: Current market price (INR) | B7: =DCF!B46 -> 1695 | D7: Profit after tax | E7: ='Income Statement'!K18 -> 12806.21 | F7: ='Income Statement'!L18 -> 13708.6 | G7: ='Income Statement'!M18 -> 16028.648
A8: Upside / (downside) to target | B8: =DCF!B57 -> -0.66076696 | D8: EPS (INR) | E8: ='Income Statement'!K19 -> 55.583498 | F8: ='Income Statement'!L19 -> 59.500189 | G8: ='Income Statement'!M19 -> 69.570023
A9: Target basis | B9: =DCF!B50 -> Perpetuity DCF | D9: EBITDA margin | E9: =E6/E5 -> 0.59036364 | F9: =F6/F5 -> 0.585 | G9: =G6/G5 -> 0.58
A10: Target horizon (months) | B10: =DCF!B51 -> 12
A11: Active scenario | B11: =Scenarios!B5 -> Base
A12: Valuation, active scenario | B12: Value
A13: Perpetuity DCF value per share (INR) | B13: =DCF!B45 -> 512.77969
A14: WACC | B14: =DCF!B27 -> 0.1256164
A15: Terminal growth | B15: =DCF!B28 -> 0.05
A16: Return on new capital in perpetuity (RONIC) | B16: =DCF!B29 -> 0.105
A17: Terminal value as % of EV | B17: =DCF!B35 -> 0.73573796
A18: Enterprise value (INR Cr) | B18: =DCF!B34 -> 163736.52
A19: Equity value (INR Cr) | B19: =DCF!B43 -> 118142.34
A21: Value per share by method | B21: INR / share
A22: Base case, perpetuity DCF | B22: =Scenarios!C44 -> 513
A23: Bull case, perpetuity DCF | B23: =Scenarios!C45 -> 691
A24: Bear case, perpetuity DCF | B24: =Scenarios!C46 -> 217
A25: Probability-weighted, perpetuity | B25: =Scenarios!D47 -> 483.5
A26: DCF at the cross-check exit multiple | B26: =DCF!B68 -> 1144.6338
A27: DCF at the alternative exit multiple | B27: =DCF!B70 -> 1616.0119
A28: Current market price | B28: =DCF!B46 -> 1695
A29: Scenario values are recorded when each case is calculated; switch Scenarios!B4 to reproduce one.

Sheet Model info
A1: Adani Ports and Special Economic Zone Ltd - three-statement model
A3: Currency | B3: INR cr
A4: Sector | B4: realestate
A5: History | B5: Mar-17 to Mar-26 (10 years)
A6: Forecast | B6: Mar-27E to Mar-31E (5 years)
A7: Depreciation basis | B7: net_block
A8: Circular solve | B8: 5 passes, residual 0
A9: Checks | B9: ALL PASS
A11: Integrity checks
A12: OK Total assets less total liabilities and equity (forecast) | B12: blocking | C12: 0 | D12: Mar-29E
A13: OK Balance sheet cash less cash flow closing cash (forecast) | B13: blocking | C13: 0 | D13: Mar-31E
A14: OK Reserves roll-forward residual (forecast) | B14: blocking | C14: 0 | D14: Mar-31E
A15: OK Net block roll-forward residual (forecast) | B15: blocking | C15: 0 | D15: Mar-31E
A16: FAIL Reserves roll-forward residual (history) | B16: advisory | C16: 22582.9 | D16: Mar-26
A17: OK Net block roll-forward residual (history) | B17: advisory | C17: 0 | D17: Mar-21
A18: OK Reconstructed CFO close to reported CFO | B18: advisory | C18: 4415.24 | D18: Mar-22
A19: OK Cash less the minimum cash balance | B19: blocking | C19: 10550.461 | D19: Mar-27E
A20: OK Revolver balance | B20: blocking | C20: 0 | D20: Mar-27E
A21: OK Net block | B21: blocking | C21: 138607.46 | D21: Mar-27E
A22: OK Shareholders' equity | B22: blocking | C22: 107697.64 | D22: Mar-27E
A23: OK Historical balance sheet ties to the source | B23: blocking | C23: 0 | D23: Mar-26
... A27: OK Dividend payout inside a plausible band | B27: advisory | C27: 0 | D27: -
A29: Notes
A30: - overrides.actuals.payables: period '_page' is not in the historical range, ignored
A31: - trade payables supplied from the annual report were netted out of other liabilities so the balance sheet still ties
A32: - no gross margin in assumptions.json: set equal to the EBITDA margin, which zeroes the opex line
A33: - built against modeling strategy: revenue_model=segment_buildup, modelability=AMBER, decision=APPROVED
A34: - block 'derived' not found in the export
A35: - block 'price' not found in the export
A36: - held at the trailing historical average (no value in assumptions.json or overrides): other_income_pct, dep_pct_nb, cwip_pct_sales, other_ca_pct, other_liab_pct, interest_income_rate, debt_growth, term_debt_repay, equity_issued, payout_ratio, min_cash
A37: - not in the source at all, held at zero for every year: exceptional
A38: - no actual for 'capex' in Mar-17: set to zero
A40: Valuation
A41: - Scenarios!B4 selects the case. The switched driver rows on Drivers are green links to it.
... A48: - EXPLAINED Reserves roll-forward residual (history) (Mar-26, INR 22,583 Cr): Share-funded NQXT acquisition (December 2025): 143,820,153 shares issued to the promoter-group vendor. Share capital rose INR 28.76 Cr (14.38 Cr shares at INR 2 face value) and the premium, about INR 1,560 a share, went to reserves. Screener records no equity issuance. Moves the valuation: no. Source: kb/annual_report/pages/page_0659.md (Consolidated Balance Sheet: Equity Share Capital 460.79 vs 432.03, AR p.660); data/financials.json

Sheet Summary
A1: Adani Ports and Special Economic Zone Ltd - Summary
A2: INR cr unless stated | built 2026-10-14 | blue = input, black = formula, green = link to another sheet
A4: Actuals | B4: Mar-17 | C4: Mar-18 | D4: Mar-19 | E4: Mar-20 | F4: Mar-21 | G4: Mar-22 | H4: Mar-23 | I4: Mar-24 | J4: Mar-25 | K4: Mar-26 | L4: Mar-27E | M4: Mar-28E | N4: Mar-29E | O4: Mar-30E | P4: Mar-31E
A5: Operating performance
A6: Revenue | B6: ='Income Statement'!B6 -> 8439.35 | C6: ='Income Statement'!C6 -> 11322.96 | D6: ='Income Statement'!D6 -> 10925.44 | E6: ='Income Statement'!E6 -> 11873.07 | F6: ='Income Statement'!F6 -> 12549.6 | G6: ='Income Statement'!G6 -> 17118.79 | H6: ='Income Statement'!H6 -> 20851.91 | I6: ='Income Statement'!I6 -> 26710.56 | ... P6: ='Income Statement'!P6 -> 78286.824
A7: Revenue growth | B7: =(IFERROR(('Income Statement'!B6)/(0),0)-1) -> -1 | C7: =(IFERROR(('Income Statement'!C6)/('Income Statement'!B6),0)-1) -> 0.34168627 | D7: =(IFERROR(('Income Statement'!D6)/('Income Statement'!C6),0)-1) -> -0.035107428 | E7: =(IFERROR(('Income Statement'!E6)/('Income Statement'!D6),0)-1) -> 0.086736095 | F7: =(IFERROR(('Income Statement'!F6)/('Income Statement'!E6),0)-1) -> 0.056980208 | G7: =(IFERROR(('Income Statement'!G6)/('Income Statement'!F6),0)-1) -> 0.36409049 | H7: =(IFERROR(('Income Statement'!H6)/('Income Statement'!G6),0)-1) -> 0.21807149 | I7: =(IFERROR(('Income Statement'!I6)/('Income Statement'!H6),0)-1) -> 0.28096467 | J7: =(IFERROR(('Income Statement'!J6)/('Income Statement'!I6),0)-1) -> 0.14094688 | ... P7: =(IFERROR(('Income Statement'!P6)/('Income Statement'!O6),0)-1) -> 0.1209
A8: EBITDA | B8: ='Income Statement'!B10 -> 5418.23 | C8: ='Income Statement'!C10 -> 7156.67 | D8: ='Income Statement'!D10 -> 6595.64 | E8: ='Income Statement'!E10 -> 5947.11 | F8: ='Income Statement'!F10 -> 8687.96 | G8: ='Income Statement'!G10 -> 9527.96 | H8: ='Income Statement'!H10 -> 10947.13 | I8: ='Income Statement'!I10 -> 15589.41 | ... P8: ='Income Statement'!P10 -> 44232.056
A9: EBITDA margin | B9: =IFERROR(('Income Statement'!B10)/('Income Statement'!B6),0) -> 0.64201982 | C9: =IFERROR(('Income Statement'!C10)/('Income Statement'!C6),0) -> 0.63204939 | D9: =IFERROR(('Income Statement'!D10)/('Income Statement'!D6),0) -> 0.60369559 | E9: =IFERROR(('Income Statement'!E10)/('Income Statement'!E6),0) -> 0.50089067 | F9: =IFERROR(('Income Statement'!F10)/('Income Statement'!F6),0) -> 0.69228979 | G9: =IFERROR(('Income Statement'!G10)/('Income Statement'!G6),0) -> 0.55657906 | H9: =IFERROR(('Income Statement'!H10)/('Income Statement'!H6),0) -> 0.52499411 | I9: =IFERROR(('Income Statement'!I10)/('Income Statement'!I6),0) -> 0.5836422 | ... P9: =IFERROR(('Income Statement'!P10)/('Income Statement'!P6),0) -> 0.565
A10: EBIT | B10: ='Income Statement'!B12 -> 4258.04 | C10: ='Income Statement'!C12 -> 5968.3 | D10: ='Income Statement'!D12 -> 5222.16 | E10: ='Income Statement'!E12 -> 4266.83 | F10: ='Income Statement'!F12 -> 6580.62 | G10: ='Income Statement'!G12 -> 6428.66 | H10: ='Income Statement'!H12 -> 7522.42 | I10: ='Income Statement'!I12 -> 11700.95 | ... P10: ='Income Statement'!P12 -> 34608.765
A11: Profit after tax | B11: ='Income Statement'!B18 -> 3911.52 | C11: ='Income Statement'!C18 -> 3673.62 | D11: ='Income Statement'!D18 -> 3990.22 | E11: ='Income Statement'!E18 -> 3763.13 | F11: ='Income Statement'!F18 -> 4994.3 | G11: ='Income Statement'!G18 -> 4886.03 | H11: ='Income Statement'!H18 -> 5308.85 | I11: ='Income Statement'!I18 -> 8110.64 | ... P11: ='Income Statement'!P18 -> 25628.194
A12: Earnings per share | B12: ='Income Statement'!B19 -> 18.887545 | C12: ='Income Statement'!C19 -> 17.738798 | D12: ='Income Statement'!D19 -> 19.267564 | E12: ='Income Statement'!E19 -> 18.521601 | F12: ='Income Statement'!F19 -> 24.581248 | G12: ='Income Statement'!G19 -> 23.130527 | H12: ='Income Statement'!H19 -> 24.576428 | I12: ='Income Statement'!I19 -> 37.546843 | ... P12: ='Income Statement'!P19 -> 111.23546
A13: Cash generation
A14: Free cash flow to the firm | B14: =(((('Income Statement'!B12*(1-Drivers!B22))+'Income Statement'!B11)-Schedules!B7)-Schedules!B12) -> -5888.795 | C14: =(((('Income Statement'!C12*(1-Drivers!C22))+'Income Statement'!C11)-Schedules!C7)-Schedules!C12) -> 1595.9536 | D14: =(((('Income Statement'!D12*(1-Drivers!D22))+'Income Statement'!D11)-Schedules!D7)-Schedules!D12) -> -2104.8209 | E14: =(((('Income Statement'!E12*(1-Drivers!E22))+'Income Statement'!E11)-Schedules!E7)-Schedules!E12) -> 643.13455 | F14: =(((('Income Statement'!F12*(1-Drivers!F22))+'Income Statement'!F11)-Schedules!F7)-Schedules!F12) -> -6448.525 | G14: =(((('Income Statement'!G12*(1-Drivers!G22))+'Income Statement'!G11)-Schedules!G7)-Schedules!G12) -> -10748.275 | H14: =(((('Income Statement'!H12*(1-Drivers!H22))+'Income Statement'!H11)-Schedules!H7)-Schedules!H12) -> -1237.1594 | I14: =(((('Income Statement'!I12*(1-Drivers!I22))+'Income Statement'!I11)-Schedules!I7)-Schedules!I12) -> 10875.116 | ... P14: =(((('Income Statement'!P12*(1-Drivers!P22))+'Income Statement'!P11)-Schedules!P7)-Schedules!P12) -> 16875.714
A15: Free cash flow to equity | B15: =(((('Income Statement'!B18+'Income Statement'!B11)-Schedules!B7)-Schedules!B12)+('Balance Sheet'!B19-0)) -> 16251.36 | C15: =(((('Income Statement'!C18+'Income Statement'!C11)-Schedules!C7)-Schedules!C12)+('Balance Sheet'!C19-'Balance Sheet'!B19)) -> 1236.45 | D15: =(((('Income Statement'!D18+'Income Statement'!D11)-Schedules!D7)-Schedules!D12)+('Balance Sheet'!D19-'Balance Sheet'!C19)) -> 3162 | E15: =(((('Income Statement'!E18+'Income Statement'!E11)-Schedules!E7)-Schedules!E12)+('Balance Sheet'!E19-'Balance Sheet'!D19)) -> 3153.6 | F15: =(((('Income Statement'!F18+'Income Statement'!F11)-Schedules!F7)-Schedules!F12)+('Balance Sheet'!F19-'Balance Sheet'!E19)) -> -1064.6 | G15: =(((('Income Statement'!G18+'Income Statement'!G11)-Schedules!G7)-Schedules!G12)+('Balance Sheet'!G19-'Balance Sheet'!F19)) -> 723.06 | H15: =(((('Income Statement'!H18+'Income Statement'!H11)-Schedules!H7)-Schedules!H12)+('Balance Sheet'!H19-'Balance Sheet'!G19)) -> 2292.83 | I15: =(((('Income Statement'!I18+'Income Statement'!I11)-Schedules!I7)-Schedules!I12)+('Balance Sheet'!I19-'Balance Sheet'!H19)) -> 5175.69 | J15: =(((('Income Statement'!J18+'Income Statement'!J11)-Schedules!J7)-Schedules!J12)+('Balance Sheet'!J19-'Balance Sheet'!I19)) -> 1716.58 | ... P15: =(((('Income Statement'!P18+'Income Statement'!P11)-Schedules!P7)-Schedules!P12)+('Balance Sheet'!P19-'Balance Sheet'!O19)) -> 19807.031
A16: EBITDA to FCFF conversion | B16: =IFERROR((B14)/('Income Statement'!B10),0) -> -1.0868485 | C16: =IFERROR((C14)/('Income Statement'!C10),0) -> 0.22300227 | D16: =IFERROR((D14)/('Income Statement'!D10),0) -> -0.31912307 | E16: =IFERROR((E14)/('Income Statement'!E10),0) -> 0.10814237 | F16: =IFERROR((F14)/('Income Statement'!F10),0) -> -0.74223696 | G16: =IFERROR((G14)/('Income Statement'!G10),0) -> -1.1280772 | H16: =IFERROR((H14)/('Income Statement'!H10),0) -> -0.11301221 | I16: =IFERROR((I14)/('Income Statement'!I10),0) -> 0.69759641 | ... P16: =IFERROR((P14)/('Income Statement'!P10),0) -> 0.38152678
A17: Leverage and returns
A18: Net debt | B18: =(('Balance Sheet'!B19-'Balance Sheet'!B6)-'Balance Sheet'!B12) -> 19076.1 | C18: =(('Balance Sheet'!C19-'Balance Sheet'!C6)-'Balance Sheet'!C12) -> 18323.57 | D18: =(('Balance Sheet'!D19-'Balance Sheet'!D6)-'Balance Sheet'!D12) -> 20961.94 | E18: =(('Balance Sheet'!E19-'Balance Sheet'!E6)-'Balance Sheet'!E12) -> 21750.46 | F18: =(('Balance Sheet'!F19-'Balance Sheet'!F6)-'Balance Sheet'!F12) -> 28918.4 | G18: =(('Balance Sheet'!G19-'Balance Sheet'!G6)-'Balance Sheet'!G12) -> 34106.6 | H18: =(('Balance Sheet'!H19-'Balance Sheet'!H6)-'Balance Sheet'!H12) -> 41668.26 | I18: =(('Balance Sheet'!I19-'Balance Sheet'!I6)-'Balance Sheet'!I12) -> 37549.7 | ... P18: =(('Balance Sheet'!P19-'Balance Sheet'!P6)-'Balance Sheet'!P12) -> 32798.18
A19: Net debt / EBITDA | B19: =IFERROR((B18)/('Income Statement'!B10),0) -> 3.5207254 | C19: =IFERROR((C18)/('Income Statement'!C10),0) -> 2.5603486 | D19: =IFERROR((D18)/('Income Statement'!D10),0) -> 3.178151 | E19: =IFERROR((E18)/('Income Statement'!E10),0) -> 3.6573159 | F19: =IFERROR((F18)/('Income Statement'!F10),0) -> 3.3285604 | G19: =IFERROR((G18)/('Income Statement'!G10),0) -> 3.579633 | H19: =IFERROR((H18)/('Income Statement'!H10),0) -> 3.8063182 | I19: =IFERROR((I18)/('Income Statement'!I10),0) -> 2.4086672 | ... P19: =IFERROR((P18)/('Income Statement'!P10),0) -> 0.74150251
A20: EBIT / interest expense | B20: =IFERROR(('Income Statement'!B12)/('Income Statement'!B14),0) -> 3.8163371 | C20: =IFERROR(('Income Statement'!C12)/('Income Statement'!C14),0) -> 3.7806114 | D20: =IFERROR(('Income Statement'!D12)/('Income Statement'!D14),0) -> 3.7699955 | E20: =IFERROR(('Income Statement'!E12)/('Income Statement'!E14),0) -> 2.1874 | F20: =IFERROR(('Income Statement'!F12)/('Income Statement'!F14),0) -> 2.9178598 | G20: =IFERROR(('Income Statement'!G12)/('Income Statement'!G14),0) -> 2.5270685 | H20: =IFERROR(('Income Statement'!H12)/('Income Statement'!H14),0) -> 3.1839044 | I20: =IFERROR(('Income Statement'!I12)/('Income Statement'!I14),0) -> 4.2814515 | ... P20: =IFERROR(('Income Statement'!P12)/('Income Statement'!P14),0) -> 5.0827788
A21: Capital employed | B21: =((('Balance Sheet'!B15+'Balance Sheet'!B16)+'Balance Sheet'!B19)-'Balance Sheet'!B6) -> 37763.44 | C21: =((('Balance Sheet'!C15+'Balance Sheet'!C16)+'Balance Sheet'!C19)-'Balance Sheet'!C6) -> 40305.44 | D21: =((('Balance Sheet'!D15+'Balance Sheet'!D16)+'Balance Sheet'!D19)-'Balance Sheet'!D6) -> 46116.56 | E21: =((('Balance Sheet'!E15+'Balance Sheet'!E16)+'Balance Sheet'!E19)-'Balance Sheet'!E6) -> 48385.42 | F21: =((('Balance Sheet'!F15+'Balance Sheet'!F16)+'Balance Sheet'!F19)-'Balance Sheet'!F6) -> 61596.28 | G21: =((('Balance Sheet'!G15+'Balance Sheet'!G16)+'Balance Sheet'!G19)-'Balance Sheet'!G6) -> 79089.03 | H21: =((('Balance Sheet'!H15+'Balance Sheet'!H16)+'Balance Sheet'!H19)-'Balance Sheet'!H6) -> 94489.3 | I21: =((('Balance Sheet'!I15+'Balance Sheet'!I16)+'Balance Sheet'!I19)-'Balance Sheet'!I6) -> 94616.6 | ... P21: =((('Balance Sheet'!P15+'Balance Sheet'!P16)+'Balance Sheet'!P19)-'Balance Sheet'!P6) -> 217219.62
A22: Post-tax ROCE | B22: =IFERROR((('Income Statement'!B12*(1-Drivers!B22)))/(AVERAGE(0,B21)),0) -> 0.21108379 | C22: =IFERROR((('Income Statement'!C12*(1-Drivers!C22)))/(AVERAGE(B21,C21)),0) -> 0.10731302 | D22: =IFERROR((('Income Statement'!D12*(1-Drivers!D22)))/(AVERAGE(C21,D21)),0) -> 0.094070934 | E22: =IFERROR((('Income Statement'!E12*(1-Drivers!E22)))/(AVERAGE(D21,E21)),0) -> 0.080071223 | F22: =IFERROR((('Income Statement'!F12*(1-Drivers!F22)))/(AVERAGE(E21,F21)),0) -> 0.094986438 | G22: =IFERROR((('Income Statement'!G12*(1-Drivers!G22)))/(AVERAGE(F21,G21)),0) -> 0.07810503 | H22: =IFERROR((('Income Statement'!H12*(1-Drivers!H22)))/(AVERAGE(G21,H21)),0) -> 0.083862203 | I22: =IFERROR((('Income Statement'!I12*(1-Drivers!I22)))/(AVERAGE(H21,I21)),0) -> 0.10413304 | J22: =IFERROR((('Income Statement'!J12*(1-Drivers!J22)))/(AVERAGE(I21,J21)),0) -> 0.11842027 | ... P22: =IFERROR((('Income Statement'!P12*(1-Drivers!P22)))/(AVERAGE(O21,P21)),0) -> 0.13432993
A23: Return on equity | B23: =IFERROR(('Income Statement'!B18)/(AVERAGE(0,Schedules!B24)),0) -> 0.44636819 | C23: =IFERROR(('Income Statement'!C18)/(AVERAGE(Schedules!B24,Schedules!C24)),0) -> 0.19119033 | D23: =IFERROR(('Income Statement'!D18)/(AVERAGE(Schedules!C24,Schedules!D24)),0) -> 0.17626488 | E23: =IFERROR(('Income Statement'!E18)/(AVERAGE(Schedules!D24,Schedules!E24)),0) -> 0.15104091 | F23: =IFERROR(('Income Statement'!F18)/(AVERAGE(Schedules!E24,Schedules!F24)),0) -> 0.17869113 | G23: =IFERROR(('Income Statement'!G18)/(AVERAGE(Schedules!F24,Schedules!G24)),0) -> 0.13522831 | H23: =IFERROR(('Income Statement'!H18)/(AVERAGE(Schedules!G24,Schedules!H24)),0) -> 0.12174714 | I23: =IFERROR(('Income Statement'!I18)/(AVERAGE(Schedules!H24,Schedules!I24)),0) -> 0.16524062 | J23: =IFERROR(('Income Statement'!J18)/(AVERAGE(Schedules!I24,Schedules!J24)),0) -> 0.19283076 | ... P23: =IFERROR(('Income Statement'!P18)/(AVERAGE(Schedules!O24,Schedules!P24)),0) -> 0.15254889

Sheet Scenarios
A1: Adani Ports and Special Economic Zone Ltd - Scenarios
A2: Change the yellow cell: every switched driver, the statements, the checks and the DCF follow
A4: Active scenario (1 Base, 2 Bull, 3 Bear) | B4: 1
A5: Active case | B5: =CHOOSE($B$4,"Base","Bull","Bear") -> Base
A7: INR cr unless stated | B7: Mar-27E | C7: Mar-28E | D7: Mar-29E | E7: Mar-30E | F7: Mar-31E
A8: Base case inputs (probability 50%)
A9: Revenue growth | B9: 0.2139 | C9: 0.1302 | D9: 0.1447 | E9: 0.1481 | F9: 0.1209
A10: EBITDA margin | B10: 0.585 | C10: 0.58 | D10: 0.575 | E10: 0.57 | F10: 0.565
A11: Capex (% sales) | B11: 0.31 | C11: 0.3 | D11: 0.29 | E11: 0.28 | F11: 0.26
A12: Effective tax rate | B12: 0.185 | C12: 0.185 | D12: 0.185 | E12: 0.185 | F12: 0.185
A13: Terminal growth | B13: 0.05
A14: Probability | B14: 0.5
A15: The assumption set above as recommended.
A17: Bull case inputs (probability 25%)
A18: Revenue growth | B18: 0.24 | C18: 0.16 | D18: 0.17 | E18: 0.17 | F18: 0.15
A19: EBITDA margin | B19: 0.595 | C19: 0.595 | D19: 0.59 | E19: 0.59 | F19: 0.585
A20: Capex (% sales) | B20: 0.3 | C20: 0.28 | D20: 0.27 | E20: 0.25 | F20: 0.23
A21: Effective tax rate | B21: 0.16 | C21: 0.16 | D21: 0.16 | E21: 0.16 | F21: 0.16
A22: Terminal growth | B22: 0.055
A23: Probability | B23: 0.25
A24: Management delivers close to Ambition 2031: the 1bn-tonne capacity target lands on time, Colombo and Vizhinjam phase 2 ramp faster than modelled, the SEZ tax shield persists longer, and capex comes in at the bottom of the guided range. Mundra concession renewal is granted on existing terms.
A26: Bear case inputs (probability 25%)
A27: Revenue growth | B27: 0.16 | C27: 0.08 | D27: 0.08 | E27: 0.08 | F27: 0.07
A28: EBITDA margin | B28: 0.57 | C28: 0.555 | D28: 0.54 | E28: 0.53 | F28: 0.52
A29: Capex (% sales) | B29: 0.34 | C29: 0.34 | D29: 0.33 | E29: 0.32 | F29: 0.3
A30: Effective tax rate | B30: 0.23 | C30: 0.23 | D30: 0.23 | E30: 0.23 | F30: 0.23
A31: Terminal growth | B31: 0.035
A32: Probability | B32: 0.25
A33: The volume-miss pattern continues and worsens: domestic cargo grows mid single digit rather than high single digit, the international book stays sub-scale at NQXT's lower realisation, and capex overshoots guidance as it did by 65% in FY24 and 33% in FY26. The SEZ tax shield unwinds to statutory. Terminal growth cut to 3.5% to reflect unresolved Mundra concession renewal beyond February 2031.
A35: Active path (feeds the Drivers sheet)
A36: Revenue growth | B36: =CHOOSE(Scenarios!$B$4,B9,B18,B27) -> 0.2139 | C36: =CHOOSE(Scenarios!$B$4,C9,C18,C27) -> 0.1302 | D36: =CHOOSE(Scenarios!$B$4,D9,D18,D27) -> 0.1447 | E36: =CHOOSE(Scenarios!$B$4,E9,E18,E27) -> 0.1481 | F36: =CHOOSE(Scenarios!$B$4,F9,F18,F27) -> 0.1209
A37: EBITDA margin | B37: =CHOOSE(Scenarios!$B$4,B10,B19,B28) -> 0.585 | C37: =CHOOSE(Scenarios!$B$4,C10,C19,C28) -> 0.58 | D37: =CHOOSE(Scenarios!$B$4,D10,D19,D28) -> 0.575 | E37: =CHOOSE(Scenarios!$B$4,E10,E19,E28) -> 0.57 | F37: =CHOOSE(Scenarios!$B$4,F10,F19,F28) -> 0.565
A38: Capex (% sales) | B38: =CHOOSE(Scenarios!$B$4,B11,B20,B29) -> 0.31 | C38: =CHOOSE(Scenarios!$B$4,C11,C20,C29) -> 0.3 | D38: =CHOOSE(Scenarios!$B$4,D11,D20,D29) -> 0.29 | E38: =CHOOSE(Scenarios!$B$4,E11,E20,E29) -> 0.28 | F38: =CHOOSE(Scenarios!$B$4,F11,F20,F29) -> 0.26
A39: Effective tax rate | B39: =CHOOSE(Scenarios!$B$4,B12,B21,B30) -> 0.185 | C39: =CHOOSE(Scenarios!$B$4,C12,C21,C30) -> 0.185 | D39: =CHOOSE(Scenarios!$B$4,D12,D21,D30) -> 0.185 | E39: =CHOOSE(Scenarios!$B$4,E12,E21,E30) -> 0.185 | F39: =CHOOSE(Scenarios!$B$4,F12,F21,F30) -> 0.185
A40: Terminal growth | B40: =CHOOSE(Scenarios!$B$4,B13,B22,B31) -> 0.05
A42: Scenario values (INR per share; recorded with the selector at each case)
A43: Case | B43: Prob. | C43: Value | D43: Weighted
A44: Base | B44: =B14 -> 0.5 | C44: 513 | D44: =B44*C44 -> 256.5
A45: Bull | B45: =B23 -> 0.25 | C45: 691 | D45: =B45*C45 -> 172.75
A46: Bear | B46: =B32 -> 0.25 | C46: 217 | D46: =B46*C46 -> 54.25
A47: Probability-weighted value | B47: =SUM(B44:B46) -> 1 | D47: =SUM(D44:D46) -> 483.5
A49: Live value, active case (DCF sheet) | B49: =DCF!B45 -> 512.77969
A50: Recorded value, active case | B50: =INDEX(C44:C46,Scenarios!$B$4) -> 513
A51: Difference (must be 0) | B51: =ROUND(B49,0)-B50 -> 0

Sheet Drivers
A1: Adani Ports and Special Economic Zone Ltd - Drivers
A2: INR cr unless stated | built 2026-10-14 | blue = input, black = formula, green = link to another sheet
A4: Actuals | B4: Mar-17 | C4: Mar-18 | D4: Mar-19 | E4: Mar-20 | F4: Mar-21 | G4: Mar-22 | H4: Mar-23 | I4: Mar-24 | J4: Mar-25 | K4: Mar-26 | L4: Mar-27E | M4: Mar-28E | N4: Mar-29E | O4: Mar-30E | P4: Mar-31E
A5: Growth and margins
A6: Revenue growth | B6: =(IFERROR(('Income Statement'!B6)/(0),0)-1) -> -1 | C6: =(IFERROR(('Income Statement'!C6)/('Income Statement'!B6),0)-1) -> 0.34168627 | D6: =(IFERROR(('Income Statement'!D6)/('Income Statement'!C6),0)-1) -> -0.035107428 | E6: =(IFERROR(('Income Statement'!E6)/('Income Statement'!D6),0)-1) -> 0.086736095 | F6: =(IFERROR(('Income Statement'!F6)/('Income Statement'!E6),0)-1) -> 0.056980208 | G6: =(IFERROR(('Income Statement'!G6)/('Income Statement'!F6),0)-1) -> 0.36409049 | H6: =(IFERROR(('Income Statement'!H6)/('Income Statement'!G6),0)-1) -> 0.21807149 | I6: =(IFERROR(('Income Statement'!I6)/('Income Statement'!H6),0)-1) -> 0.28096467 | J6: =(IFERROR(('Income Statement'!J6)/('Income Statement'!I6),0)-1) -> 0.14094688 | K6: =(IFERROR(('Income Statement'!K6)/('Income Statement'!J6),0)-1) -> 0.27105334 | L6: =Scenarios!B36 -> 0.2139 | M6: =Scenarios!C36 -> 0.1302 | N6: =Scenarios!D36 -> 0.1447 | O6: =Scenarios!E36 -> 0.1481 | P6: =Scenarios!F36 -> 0.1209
A7: Gross margin | B7: =IFERROR(('Income Statement'!B8)/('Income Statement'!B6),0) -> 0.73728427 | C7: =IFERROR(('Income Statement'!C8)/('Income Statement'!C6),0) -> 0.70983029 | D7: =IFERROR(('Income Statement'!D8)/('Income Statement'!D6),0) -> 0.74169004 | E7: =IFERROR(('Income Statement'!E8)/('Income Statement'!E6),0) -> 0.73327791 | F7: =IFERROR(('Income Statement'!F8)/('Income Statement'!F6),0) -> 0.73469274 | G7: =IFERROR(('Income Statement'!G8)/('Income Statement'!G6),0) -> 0.71104675 | H7: =IFERROR(('Income Statement'!H8)/('Income Statement'!H6),0) -> 0.72339704 | I7: =IFERROR(('Income Statement'!I8)/('Income Statement'!I6),0) -> 0.72757591 | ... K7: =IFERROR(('Income Statement'!K8)/('Income Statement'!K6),0) -> 0.70226796 | L7: 0.702 | M7: 0.702 | N7: 0.702 | O7: 0.702 | P7: 0.702
A8: EBITDA margin | B8: =IFERROR(('Income Statement'!B10)/('Income Statement'!B6),0) -> 0.64201982 | C8: =IFERROR(('Income Statement'!C10)/('Income Statement'!C6),0) -> 0.63204939 | D8: =IFERROR(('Income Statement'!D10)/('Income Statement'!D6),0) -> 0.60369559 | E8: =IFERROR(('Income Statement'!E10)/('Income Statement'!E6),0) -> 0.50089067 | F8: =IFERROR(('Income Statement'!F10)/('Income Statement'!F6),0) -> 0.69228979 | G8: =IFERROR(('Income Statement'!G10)/('Income Statement'!G6),0) -> 0.55657906 | H8: =IFERROR(('Income Statement'!H10)/('Income Statement'!H6),0) -> 0.52499411 | I8: =IFERROR(('Income Statement'!I10)/('Income Statement'!I6),0) -> 0.5836422 | ... K8: =IFERROR(('Income Statement'!K10)/('Income Statement'!K6),0) -> 0.59036364 | L8: =Scenarios!B37 -> 0.585 | M8: =Scenarios!C37 -> 0.58 | N8: =Scenarios!D37 -> 0.575 | O8: =Scenarios!E37 -> 0.57 | P8: =Scenarios!F37 -> 0.565
A9: Other income (% sales) | B9: =IFERROR(('Income Statement'!B13)/('Income Statement'!B6),0) -> 0.12282581 | C9: =IFERROR(('Income Statement'!C13)/('Income Statement'!C6),0) -> 0.074582088 | D9: =IFERROR(('Income Statement'!D13)/('Income Statement'!D6),0) -> 0.1180044 | E9: =IFERROR(('Income Statement'!E13)/('Income Statement'!E6),0) -> 0.16236155 | F9: =IFERROR(('Income Statement'!F13)/('Income Statement'!F6),0) -> 0.15671256 | G9: =IFERROR(('Income Statement'!G13)/('Income Statement'!G6),0) -> 0.10704028 | H9: =IFERROR(('Income Statement'!H13)/('Income Statement'!H6),0) -> 0.015687292 | I9: =IFERROR(('Income Statement'!I13)/('Income Statement'!I6),0) -> 0.025104678 | ... K9: =IFERROR(('Income Statement'!K13)/('Income Statement'!K6),0) -> 0.055548915 | L9: 0.046571 | M9: 0.046571 | N9: 0.046571 | O9: 0.046571 | P9: 0.046571
A10: Capital expenditure and depreciation
A11: Capex (% sales) | B11: =IFERROR((Schedules!B7)/('Income Statement'!B6),0) -> 0 | C11: =IFERROR((Schedules!C7)/('Income Statement'!C6),0) -> 0.24771614 | D11: =IFERROR((Schedules!D7)/('Income Statement'!D6),0) -> 0.62467873 | E11: =IFERROR((Schedules!E7)/('Income Statement'!E6),0) -> 0.52836966 | F11: =IFERROR((Schedules!F7)/('Income Statement'!F6),0) -> 1.4091118 | G11: =IFERROR((Schedules!G7)/('Income Statement'!G6),0) -> 1.014164 | H11: =IFERROR((Schedules!H7)/('Income Statement'!H6),0) -> 0.62802496 | I11: =IFERROR((Schedules!I7)/('Income Statement'!I6),0) -> 0.25505044 | ... K11: =IFERROR((Schedules!K7)/('Income Statement'!K6),0) -> 1.2276395 | L11: =Scenarios!B38 -> 0.31 | M11: =Scenarios!C38 -> 0.3 | N11: =Scenarios!D38 -> 0.29 | O11: =Scenarios!E38 -> 0.28 | P11: =Scenarios!F38 -> 0.26
A12: Depreciation (% opening net block) | B12: =IFERROR(('Income Statement'!B11)/(0),0) -> 0 | C12: =IFERROR(('Income Statement'!C11)/('Balance Sheet'!B10),0) -> 0.056445247 | D12: =IFERROR(('Income Statement'!D11)/('Balance Sheet'!C10),0) -> 0.060585769 | E12: =IFERROR(('Income Statement'!E11)/('Balance Sheet'!D10),0) -> 0.059750895 | F12: =IFERROR(('Income Statement'!F11)/('Balance Sheet'!E10),0) -> 0.064416065 | G12: =IFERROR(('Income Statement'!G11)/('Balance Sheet'!F10),0) -> 0.064179714 | H12: =IFERROR(('Income Statement'!H11)/('Balance Sheet'!G10),0) -> 0.054749003 | I12: =IFERROR(('Income Statement'!I11)/('Balance Sheet'!H10),0) -> 0.053839091 | J12: =IFERROR(('Income Statement'!J11)/('Balance Sheet'!I10),0) -> 0.058270893 | K12: =IFERROR(('Income Statement'!K11)/('Balance Sheet'!J10),0) -> 0.061566688 | L12: 0.057892 | M12: 0.057892 | N12: 0.057892 | O12: 0.057892 | P12: 0.057892
A13: Depreciation (% sales) | B13: =IFERROR(('Income Statement'!B11)/('Income Statement'!B6),0) -> 0.13747386 | C13: =IFERROR(('Income Statement'!C11)/('Income Statement'!C6),0) -> 0.10495224 | D13: =IFERROR(('Income Statement'!D11)/('Income Statement'!D6),0) -> 0.12571393 | E13: =IFERROR(('Income Statement'!E11)/('Income Statement'!E6),0) -> 0.14152026 | F13: =IFERROR(('Income Statement'!F11)/('Income Statement'!F6),0) -> 0.16792089 | G13: =IFERROR(('Income Statement'!G11)/('Income Statement'!G6),0) -> 0.18104667 | H13: =IFERROR(('Income Statement'!H11)/('Income Statement'!H6),0) -> 0.16423963 | I13: =IFERROR(('Income Statement'!I11)/('Income Statement'!I6),0) -> 0.14557763 | ... K13: =IFERROR(('Income Statement'!K11)/('Income Statement'!K6),0) -> 0.14243631 | L13: 0.145 | M13: 0.145 | N13: 0.148 | O13: 0.15 | P13: 0.152
A14: CWIP (% sales) | B14: =IFERROR(('Balance Sheet'!B11)/('Income Statement'!B6),0) -> 0.53487176 | C14: =IFERROR(('Balance Sheet'!C11)/('Income Statement'!C6),0) -> 0.40143743 | D14: =IFERROR(('Balance Sheet'!D11)/('Income Statement'!D6),0) -> 0.41037066 | E14: =IFERROR(('Balance Sheet'!E11)/('Income Statement'!E6),0) -> 0.27089287 | F14: =IFERROR(('Balance Sheet'!F11)/('Income Statement'!F6),0) -> 0.29460142 | G14: =IFERROR(('Balance Sheet'!G11)/('Income Statement'!G6),0) -> 0.23499909 | H14: =IFERROR(('Balance Sheet'!H11)/('Income Statement'!H6),0) -> 0.31828116 | I14: =IFERROR(('Balance Sheet'!I11)/('Income Statement'!I6),0) -> 0.40942945 | ... K14: =IFERROR(('Balance Sheet'!K11)/('Income Statement'!K6),0) -> 0.32757965 | L14: 0.373709 | M14: 0.373709 | N14: 0.373709 | O14: 0.373709 | P14: 0.373709
A15: Working capital
A16: Receivable days | B16: =(IFERROR(('Balance Sheet'!B7)/('Income Statement'!B6),0)*365) -> 116.47122 | C16: =(IFERROR(('Balance Sheet'!C7)/('Income Statement'!C6),0)*365) -> 138.93162 | D16: =(IFERROR(('Balance Sheet'!D7)/('Income Statement'!D6),0)*365) -> 93.197702 | E16: =(IFERROR(('Balance Sheet'!E7)/('Income Statement'!E6),0)*365) -> 98.439671 | F16: =(IFERROR(('Balance Sheet'!F7)/('Income Statement'!F6),0)*365) -> 85.093083 | G16: =(IFERROR(('Balance Sheet'!G7)/('Income Statement'!G6),0)*365) -> 53.75474 | H16: =(IFERROR(('Balance Sheet'!H7)/('Income Statement'!H6),0)*365) -> 69.266103 | I16: =(IFERROR(('Balance Sheet'!I7)/('Income Statement'!I6),0)*365) -> 50.108762 | ... K16: =(IFERROR(('Balance Sheet'!K7)/('Income Statement'!K6),0)*365) -> 60.141495 | L16: 58 | M16: 58 | N16: 58 | O16: 58 | P16: 58
A17: Inventory days | B17: =(IFERROR(('Balance Sheet'!B8)/('Income Statement'!B7),0)*365) -> 108.17394 | C17: =(IFERROR(('Balance Sheet'!C8)/('Income Statement'!C7),0)*365) -> 57.799795 | D17: =(IFERROR(('Balance Sheet'!D8)/('Income Statement'!D7),0)*365) -> 104.33117 | E17: =(IFERROR(('Balance Sheet'!E8)/('Income Statement'!E7),0)*365) -> 33.226559 | F17: =(IFERROR(('Balance Sheet'!F8)/('Income Statement'!F7),0)*365) -> 108.73262 | G17: =(IFERROR(('Balance Sheet'!G8)/('Income Statement'!G7),0)*365) -> 29.19392 | H17: =(IFERROR(('Balance Sheet'!H8)/('Income Statement'!H7),0)*365) -> 28.602224 | I17: =(IFERROR(('Balance Sheet'!I8)/('Income Statement'!I7),0)*365) -> 21.945847 | ... K17: =(IFERROR(('Balance Sheet'!K8)/('Income Statement'!K7),0)*365) -> 21.67932 | L17: 21.7 | M17: 21.7 | N17: 21.7 | O17: 21.7 | P17: 21.7
A18: Payable days | B18: =(IFERROR(('Balance Sheet'!B20)/('Income Statement'!B7),0)*365) -> 0 | C18: =(IFERROR(('Balance Sheet'!C20)/('Income Statement'!C7),0)*365) -> 0 | D18: =(IFERROR(('Balance Sheet'!D20)/('Income Statement'!D7),0)*365) -> 0 | E18: =(IFERROR(('Balance Sheet'!E20)/('Income Statement'!E7),0)*365) -> 0 | F18: =(IFERROR(('Balance Sheet'!F20)/('Income Statement'!F7),0)*365) -> 0 | G18: =(IFERROR(('Balance Sheet'!G20)/('Income Statement'!G7),0)*365) -> 0 | H18: =(IFERROR(('Balance Sheet'!H20)/('Income Statement'!H7),0)*365) -> 0 | I18: =(IFERROR(('Balance Sheet'!I20)/('Income Statement'!I7),0)*365) -> 0 | ... K18: =(IFERROR(('Balance Sheet'!K20)/('Income Statement'!K7),0)*365) -> 86.598282 | L18: 86.6 | M18: 86.6 | N18: 86.6 | O18: 86.6 | P18: 86.6
A19: Other current assets (% sales) | B19: =IFERROR(('Balance Sheet'!B9)/('Income Statement'!B6),0) -> 1.3405843 | C19: =IFERROR(('Balance Sheet'!C9)/('Income Statement'!C6),0) -> 0.9838929 | D19: =IFERROR(('Balance Sheet'!D9)/('Income Statement'!D6),0) -> 1.222888 | E19: =IFERROR(('Balance Sheet'!E9)/('Income Statement'!E6),0) -> 1.1794405 | F19: =IFERROR(('Balance Sheet'!F9)/('Income Statement'!F6),0) -> 0.93543619 | G19: =IFERROR(('Balance Sheet'!G9)/('Income Statement'!G6),0) -> 0.87665308 | H19: =IFERROR(('Balance Sheet'!H9)/('Income Statement'!H6),0) -> 0.84057959 | I19: =IFERROR(('Balance Sheet'!I9)/('Income Statement'!I6),0) -> 0.55746903 | ... K19: =IFERROR(('Balance Sheet'!K9)/('Income Statement'!K6),0) -> 0.45842073 | L19: 0.512548 | M19: 0.512548 | N19: 0.512548 | O19: 0.512548 | P19: 0.512548
A20: Other liabilities (% sales) | B20: =IFERROR(('Balance Sheet'!B21)/('Income Statement'!B6),0) -> 0.43002482 | C20: =IFERROR(('Balance Sheet'!C21)/('Income Statement'!C6),0) -> 0.34970803 | D20: =IFERROR(('Balance Sheet'!D21)/('Income Statement'!D6),0) -> 0.38694734 | E20: =IFERROR(('Balance Sheet'!E21)/('Income Statement'!E6),0) -> 0.52365732 | F20: =IFERROR(('Balance Sheet'!F21)/('Income Statement'!F6),0) -> 0.66017005 | G20: =IFERROR(('Balance Sheet'!G21)/('Income Statement'!G6),0) -> 0.50071004 | H20: =IFERROR(('Balance Sheet'!H21)/('Income Statement'!H6),0) -> 0.6589123 | I20: =IFERROR(('Balance Sheet'!I21)/('Income Statement'!I6),0) -> 0.55224301 | ... K20: =IFERROR(('Balance Sheet'!K21)/('Income Statement'!K6),0) -> 0.53795239 | L20: 0.54751 | M20: 0.54751 | N20: 0.54751 | O20: 0.54751 | P20: 0.54751
A21: Financing, tax and distribution
A22: Effective tax rate | B22: =IFERROR(('Income Statement'!B17)/('Income Statement'!B16),0) -> 0.063976625 | C22: =IFERROR(('Income Statement'!C17)/('Income Statement'!C16),0) -> 0.29814124 | D22: =IFERROR(('Income Statement'!D17)/('Income Statement'!D16),0) -> 0.22160578 | E22: =IFERROR(('Income Statement'!E17)/('Income Statement'!E16),0) -> 0.11328913 | F22: =IFERROR(('Income Statement'!F17)/('Income Statement'!F16),0) -> 0.20624729 | G22: =IFERROR(('Income Statement'!G17)/('Income Statement'!G16),0) -> 0.14537164 | H22: =IFERROR(('Income Statement'!H17)/('Income Statement'!H16),0) -> 0.032448254 | I22: =IFERROR(('Income Statement'!I17)/('Income Statement'!I16),0) -> 0.15852248 | ... K22: =IFERROR(('Income Statement'!K17)/('Income Statement'!K16),0) -> 0.13754532 | L22: =Scenarios!B39 -> 0.185 | M22: =Scenarios!C39 -> 0.185 | N22: =Scenarios!D39 -> 0.185 | O22: =Scenarios!E39 -> 0.185 | P22: =Scenarios!F39 -> 0.185
A23: Interest rate on debt | B23: =IFERROR(('Income Statement'!B14)/(AVERAGE(0,'Balance Sheet'!B19)),0) -> 0.10045259 | C23: =IFERROR(('Income Statement'!C14)/(AVERAGE('Balance Sheet'!B19,'Balance Sheet'!C19)),0) -> 0.070816857 | D23: =IFERROR(('Income Statement'!D14)/(AVERAGE('Balance Sheet'!C19,'Balance Sheet'!D19)),0) -> 0.055317344 | E23: =IFERROR(('Income Statement'!E14)/(AVERAGE('Balance Sheet'!D19,'Balance Sheet'!E19)),0) -> 0.067317 | F23: =IFERROR(('Income Statement'!F14)/(AVERAGE('Balance Sheet'!E19,'Balance Sheet'!F19)),0) -> 0.068241155 | G23: =IFERROR(('Income Statement'!G14)/(AVERAGE('Balance Sheet'!F19,'Balance Sheet'!G19)),0) -> 0.060721269 | H23: =IFERROR(('Income Statement'!H14)/(AVERAGE('Balance Sheet'!G19,'Balance Sheet'!H19)),0) -> 0.046614659 | I23: =IFERROR(('Income Statement'!I14)/(AVERAGE('Balance Sheet'!H19,'Balance Sheet'!I19)),0) -> 0.053116065 | J23: =IFERROR(('Income Statement'!J14)/(AVERAGE('Balance Sheet'!I19,'Balance Sheet'!J19)),0) -> 0.055646315 | K23: =IFERROR(('Income Statement'!K14)/(AVERAGE('Balance Sheet'!J19,'Balance Sheet'!K19)),0) -> 0.080807909 | L23: 0.08 | M23: 0.08 | N23: 0.08 | O23: 0.08 | P23: 0.08
A24: Yield on cash and investments | B24: =0 -> 0 | C24: =0 -> 0 | D24: =0 -> 0 | E24: =0 -> 0 | F24: =0 -> 0 | G24: =0 -> 0 | H24: =0 -> 0 | I24: =0 -> 0 | ... K24: =0 -> 0 | L24: 0 | M24: 0 | N24: 0 | O24: 0 | P24: 0
A25: Term debt growth | B25: =(IFERROR(('Balance Sheet'!B17)/(0),0)-1) -> -1 | C25: =(IFERROR(('Balance Sheet'!C17)/('Balance Sheet'!B17),0)-1) -> 0.0070126126 | D25: =(IFERROR(('Balance Sheet'!D17)/('Balance Sheet'!C17),0)-1) -> 0.23877919 | E25: =(IFERROR(('Balance Sheet'!E17)/('Balance Sheet'!D17),0)-1) -> 0.091325852 | F25: =(IFERROR(('Balance Sheet'!F17)/('Balance Sheet'!E17),0)-1) -> 0.18560117 | G25: =(IFERROR(('Balance Sheet'!G17)/('Balance Sheet'!F17),0)-1) -> 0.33689329 | H25: =(IFERROR(('Balance Sheet'!H17)/('Balance Sheet'!G17),0)-1) -> 0.11472825 | I25: =(IFERROR(('Balance Sheet'!I17)/('Balance Sheet'!H17),0)-1) -> -0.074184296 | J25: =(IFERROR(('Balance Sheet'!J17)/('Balance Sheet'!I17),0)-1) -> 0.043470377 | K25: =(IFERROR(('Balance Sheet'!K17)/('Balance Sheet'!J17),0)-1) -> 0.23139522 | L25: 0.066894 | M25: 0.066894 | N25: 0.066894 | O25: 0.066894 | P25: 0.066894
A26: Scheduled debt repayment | B26: =0 -> 0 | C26: =0 -> 0 | D26: =0 -> 0 | E26: =0 -> 0 | F26: =0 -> 0 | G26: =0 -> 0 | H26: =0 -> 0 | I26: =0 -> 0 | ... K26: =0 -> 0 | L26: 0 | M26: 0 | N26: 0 | O26: 0 | P26: 0
A27: Equity issued | B27: =0 -> 0 | C27: =0 -> 0 | D27: =0 -> 0 | E27: =0 -> 0 | F27: =0 -> 0 | G27: =0 -> 0 | H27: =0 -> 0 | I27: =0 -> 0 | ... K27: =0 -> 0 | L27: 0 | M27: 0 | N27: 0 | O27: 0 | P27: 0
A28: Dividend payout | B28: =IFERROR((Schedules!B22)/('Income Statement'!B18),0) -> 0.068827463 | C28: =IFERROR((Schedules!C22)/('Income Statement'!C18),0) -> 0.1127471 | D28: =IFERROR((Schedules!D22)/('Income Statement'!D18),0) -> 0.01038038 | E28: =IFERROR((Schedules!E22)/('Income Statement'!E18),0) -> 0.17277107 | F28: =IFERROR((Schedules!F22)/('Income Statement'!F18),0) -> 0.20340788 | G28: =IFERROR((Schedules!G22)/('Income Statement'!G18),0) -> 0.21616322 | H28: =IFERROR((Schedules!H22)/('Income Statement'!H18),0) -> 0.20344896 | I28: =IFERROR((Schedules!I22)/('Income Statement'!I18),0) -> 0.1598012 | ... K28: =IFERROR((Schedules!K22)/('Income Statement'!K18),0) -> 0.13493141 | L28: 0.143684 | M28: 0.143684 | N28: 0.143684 | O28: 0.143684 | P28: 0.143684
A29: Minimum cash balance | B29: =0 -> 0 | C29: =0 -> 0 | D29: =0 -> 0 | E29: =0 -> 0 | F29: =0 -> 0 | G29: =0 -> 0 | H29: =0 -> 0 | I29: =0 -> 0 | ... K29: =0 -> 0 | L29: 0 | M29: 0 | N29: 0 | O29: 0 | P29: 0

Sheet Income Statement
A1: Adani Ports and Special Economic Zone Ltd - Income Statement
A2: INR cr unless stated | built 2026-10-14 | blue = input, black = formula, green = link to another sheet
A4: Actuals | B4: Mar-17 | C4: Mar-18 | D4: Mar-19 | E4: Mar-20 | F4: Mar-21 | G4: Mar-22 | H4: Mar-23 | I4: Mar-24 | J4: Mar-25 | K4: Mar-26 | L4: Mar-27E | M4: Mar-28E | N4: Mar-29E | O4: Mar-30E | P4: Mar-31E
A5: Income statement
A6: Revenue | B6: 8439.35 | C6: 11322.96 | D6: 10925.44 | E6: 11873.07 | F6: 12549.6 | G6: 17118.79 | H6: 20851.91 | I6: 26710.56 | J6: 30475.33 | K6: 38735.77 | L6: =(K6*(1+Drivers!L6)) -> 47021.351 | M6: =(L6*(1+Drivers!M6)) -> 53143.531 | N6: =(M6*(1+Drivers!N6)) -> 60833.4 | O6: =(N6*(1+Drivers!O6)) -> 69842.827 | P6: =(O6*(1+Drivers!P6)) -> 78286.824
A7: Cost of goods sold | B7: 2217.15 | C7: 3285.58 | D7: 2822.15 | E7: 3166.81 | F7: 3329.5 | G7: 4946.53 | H7: 5767.7 | I7: 7276.6 | J7: 8271.03 | K7: 11532.88 | L7: =(L6*(1-Drivers!L7)) -> 14012.363 | M7: =(M6*(1-Drivers!M7)) -> 15836.772 | N7: =(N6*(1-Drivers!N7)) -> 18128.353 | O7: =(O6*(1-Drivers!O7)) -> 20813.162 | P7: =(P6*(1-Drivers!P7)) -> 23329.474
A8: Gross profit | B8: =(B6-B7) -> 6222.2 | C8: =(C6-C7) -> 8037.38 | D8: =(D6-D7) -> 8103.29 | E8: =(E6-E7) -> 8706.26 | F8: =(F6-F7) -> 9220.1 | G8: =(G6-G7) -> 12172.26 | H8: =(H6-H7) -> 15084.21 | I8: =(I6-I7) -> 19433.96 | ... P8: =(P6-P7) -> 54957.351
A9: Operating expenses | B9: =(B8-B10) -> 803.97 | C9: =(C8-C10) -> 880.71 | D9: =(D8-D10) -> 1507.65 | E9: =(E8-E10) -> 2759.15 | F9: =(F8-F10) -> 532.14 | G9: =(G8-G10) -> 2644.3 | H9: =(H8-H10) -> 4137.08 | I9: =(I8-I10) -> 3844.55 | ... P9: =(P8-P10) -> 10725.295
A10: EBITDA | B10: 5418.23 | C10: 7156.67 | D10: 6595.64 | E10: 5947.11 | F10: 8687.96 | G10: 9527.96 | H10: 10947.13 | I10: 15589.41 | J10: 18421.37 | K10: 22868.19 | L10: =(L6*Drivers!L8) -> 27507.49 | M10: =(M6*Drivers!M8) -> 30823.248 | N10: =(N6*Drivers!N8) -> 34979.205 | O10: =(O6*Drivers!O8) -> 39810.411 | P10: =(P6*Drivers!P8) -> 44232.056
A11: Depreciation and amortisation | B11: 1160.19 | C11: 1188.37 | D11: 1373.48 | E11: 1680.28 | F11: 2107.34 | G11: 3099.3 | H11: 3424.71 | I11: 3888.46 | J11: 4378.93 | K11: 5517.38 | L11: =MIN((Drivers!L12*'Balance Sheet'!K10),('Balance Sheet'!K10+Schedules!L7)) -> 7621.6265 | M11: =MIN((Drivers!M12*'Balance Sheet'!L10),('Balance Sheet'!L10+Schedules!M7)) -> 8024.2649 | N11: =MIN((Drivers!N12*'Balance Sheet'!M10),('Balance Sheet'!M10+Schedules!N7)) -> 8482.6998 | O11: =MIN((Drivers!O12*'Balance Sheet'!N10),('Balance Sheet'!N10+Schedules!O7)) -> 9012.9318 | P11: =MIN((Drivers!P12*'Balance Sheet'!O10),('Balance Sheet'!O10+Schedules!P7)) -> 9623.2906
A12: EBIT | B12: =(B10-B11) -> 4258.04 | C12: =(C10-C11) -> 5968.3 | D12: =(D10-D11) -> 5222.16 | E12: =(E10-E11) -> 4266.83 | F12: =(F10-F11) -> 6580.62 | G12: =(G10-G11) -> 6428.66 | H12: =(H10-H11) -> 7522.42 | I12: =(I10-I11) -> 11700.95 | ... P12: =(P10-P11) -> 34608.765
A13: Other income | B13: 1036.57 | C13: 844.49 | D13: 1289.25 | E13: 1927.73 | F13: 1966.68 | G13: 1832.4 | H13: 327.11 | I13: 670.56 | J13: 1799.85 | K13: 2151.73 | L13: =((L6*Drivers!L9)+(Drivers!L24*AVERAGE('Balance Sheet'!K6,'Balance Sheet'!L6))) -> 2189.8313 | M13: =((M6*Drivers!M9)+(Drivers!M24*AVERAGE('Balance Sheet'!L6,'Balance Sheet'!M6))) -> 2474.9474 | N13: =((N6*Drivers!N9)+(Drivers!N24*AVERAGE('Balance Sheet'!M6,'Balance Sheet'!N6))) -> 2833.0723 | O13: =((O6*Drivers!O9)+(Drivers!O24*AVERAGE('Balance Sheet'!N6,'Balance Sheet'!O6))) -> 3252.6503 | P13: =((P6*Drivers!P9)+(Drivers!P24*AVERAGE('Balance Sheet'!O6,'Balance Sheet'!P6))) -> 3645.8957
A14: Interest expense | B14: 1115.74 | C14: 1578.66 | D14: 1385.19 | E14: 1950.64 | F14: 2255.29 | G14: 2543.92 | H14: 2362.64 | I14: 2732.94 | J14: 2812.67 | K14: 4653.98 | L14: =(Drivers!L23*AVERAGE('Balance Sheet'!K19,'Balance Sheet'!L19)) -> 5255.3277 | M14: =(Drivers!M23*AVERAGE('Balance Sheet'!L19,'Balance Sheet'!M19)) -> 5606.8776 | N14: =(Drivers!N23*AVERAGE('Balance Sheet'!M19,'Balance Sheet'!N19)) -> 5981.944 | O14: =(Drivers!O23*AVERAGE('Balance Sheet'!N19,'Balance Sheet'!O19)) -> 6382.1002 | P14: =(Drivers!P23*AVERAGE('Balance Sheet'!O19,'Balance Sheet'!P19)) -> 6809.0244
A15: Exceptional items | B15: 0 | C15: 0 | D15: 0 | E15: 0 | F15: 0 | G15: 0 | H15: 0 | I15: 0 | J15: 0 | K15: 0 | L15: =0 -> 0 | M15: =0 -> 0 | N15: =0 -> 0 | O15: =0 -> 0 | P15: =0 -> 0
A16: Profit before tax | B16: 4178.87 | C16: 5234.13 | D16: 5126.22 | E16: 4243.92 | F16: 6292.01 | G16: 5717.14 | H16: 5486.89 | I16: 9638.57 | J16: 13029.62 | K16: 14848.56 | L16: =(((L12+L13)-L14)+L15) -> 16820.368 | M16: =(((M12+M13)-M14)+M15) -> 19667.053 | N16: =(((N12+N13)-N14)+N15) -> 23347.633 | O16: =(((O12+O13)-O14)+O15) -> 27668.029 | P16: =(((P12+P13)-P14)+P15) -> 31445.636
A17: Tax | B17: 267.35 | C17: 1560.51 | D17: 1136 | E17: 480.79 | F17: 1297.71 | G17: 831.11 | H17: 178.04 | I17: 1527.93 | J17: 1937.31 | K17: 2042.35 | L17: =(L16*Drivers!L22) -> 3111.768 | M17: =(M16*Drivers!M22) -> 3638.4048 | N17: =(N16*Drivers!N22) -> 4319.3122 | O17: =(O16*Drivers!O22) -> 5118.5854 | P17: =(P16*Drivers!P22) -> 5817.4427
A18: Profit after tax | B18: 3911.52 | C18: 3673.62 | D18: 3990.22 | E18: 3763.13 | F18: 4994.3 | G18: 4886.03 | H18: 5308.85 | I18: 8110.64 | J18: 11092.31 | K18: 12806.21 | L18: =(L16-L17) -> 13708.6 | M18: =(M16-M17) -> 16028.648 | N18: =(N16-N17) -> 19028.321 | O18: =(O16-O17) -> 22549.444 | P18: =(P16-P17) -> 25628.194
A19: Earnings per share | B19: =IFERROR((B18)/(Schedules!B23),0) -> 18.887545 | C19: =IFERROR((C18)/(Schedules!C23),0) -> 17.738798 | D19: =IFERROR((D18)/(Schedules!D23),0) -> 19.267564 | E19: =IFERROR((E18)/(Schedules!E23),0) -> 18.521601 | F19: =IFERROR((F18)/(Schedules!F23),0) -> 24.581248 | G19: =IFERROR((G18)/(Schedules!G23),0) -> 23.130527 | H19: =IFERROR((H18)/(Schedules!H23),0) -> 24.576428 | I19: =IFERROR((I18)/(Schedules!I23),0) -> 37.546843 | ... P19: =IFERROR((P18)/(Schedules!P23),0) -> 111.23546

Sheet Balance Sheet
A1: Adani Ports and Special Economic Zone Ltd - Balance Sheet
A2: INR cr unless stated | built 2026-10-14 | blue = input, black = formula, green = link to another sheet
A4: Actuals | B4: Mar-17 | C4: Mar-18 | D4: Mar-19 | E4: Mar-20 | F4: Mar-21 | G4: Mar-22 | H4: Mar-23 | I4: Mar-24 | J4: Mar-25 | K4: Mar-26 | L4: Mar-27E | M4: Mar-28E | N4: Mar-29E | O4: Mar-30E | P4: Mar-31E
A5: Assets
A6: Cash and bank | B6: 1976.8 | C6: 2967.55 | D6: 5967.3 | E6: 7313.86 | F6: 4700.78 | G6: 10667.41 | H6: 4334.31 | I6: 7631.88 | J6: 6605.97 | K6: 8483.51 | L6: =(K6+'Cash Flow'!L21) -> 10550.478 | M6: =(L6+'Cash Flow'!M21) -> 18171.553 | N6: =(M6+'Cash Flow'!N21) -> 26727.479 | O6: =(N6+'Cash Flow'!O21) -> 36651.537 | P6: =(O6+'Cash Flow'!P21) -> 49620.609
A7: Trade receivables | B7: 2692.99 | C7: 4309.91 | D7: 2789.66 | E7: 3202.14 | F7: 2925.71 | G7: 2521.14 | H7: 3957.07 | I7: 3666.94 | J7: 4432.36 | K7: 6382.54 | L7: =(IFERROR((Drivers!L16)/(365),0)*'Income Statement'!L6) -> 7471.8859 | M7: =(IFERROR((Drivers!M16)/(365),0)*'Income Statement'!M6) -> 8444.7255 | N7: =(IFERROR((Drivers!N16)/(365),0)*'Income Statement'!N6) -> 9666.6773 | O7: =(IFERROR((Drivers!O16)/(365),0)*'Income Statement'!O6) -> 11098.312 | P7: =(IFERROR((Drivers!P16)/(365),0)*'Income Statement'!P6) -> 12440.098
A8: Inventories | B8: 657.09 | C8: 520.29 | D8: 806.68 | E8: 288.28 | F8: 991.85 | G8: 395.64 | H8: 451.97 | I8: 437.51 | J8: 521.8 | K8: 685 | L8: =(IFERROR((Drivers!L17)/(365),0)*'Income Statement'!L7) -> 833.06375 | M8: =(IFERROR((Drivers!M17)/(365),0)*'Income Statement'!M7) -> 941.52865 | N8: =(IFERROR((Drivers!N17)/(365),0)*'Income Statement'!N7) -> 1077.7678 | O8: =(IFERROR((Drivers!O17)/(365),0)*'Income Statement'!O7) -> 1237.3853 | P8: =(IFERROR((Drivers!P17)/(365),0)*'Income Statement'!P7) -> 1386.9851
A9: Other current assets | B9: 11313.66 | C9: 11140.58 | D9: 13360.59 | E9: 14003.58 | F9: 11739.35 | G9: 15007.24 | H9: 17527.69 | I9: 14890.31 | J9: 15900.65 | K9: 17757.28 | L9: =('Income Statement'!L6*Drivers!L19) -> 24100.7 | M9: =('Income Statement'!M6*Drivers!M19) -> 27238.611 | N9: =('Income Statement'!N6*Drivers!N19) -> 31180.038 | O9: =('Income Statement'!O6*Drivers!O19) -> 35797.801 | P9: =('Income Statement'!P6*Drivers!P19) -> 40125.755
A10: Net fixed assets | B10: 21053.5 | C10: 22670.01 | D10: 28121.42 | E10: 32714.51 | F10: 48290.96 | G10: 62552.92 | H10: 72223.73 | I10: 75147.81 | J10: 89616.32 | K10: 131652.5 | L10: =((K10+Schedules!L7)-'Income Statement'!L11) -> 138607.49 | M10: =((L10+Schedules!M7)-'Income Statement'!M11) -> 146526.29 | N10: =((M10+Schedules!N7)-'Income Statement'!N11) -> 155685.27 | O10: =((N10+Schedules!O7)-'Income Statement'!O11) -> 166228.33 | P10: =((O10+Schedules!P7)-'Income Statement'!P11) -> 176959.62
A11: Capital work in progress | B11: 4513.97 | C11: 4545.46 | D11: 4483.48 | E11: 3216.33 | F11: 3697.13 | G11: 4022.9 | H11: 6636.77 | I11: 10936.09 | J11: 11706.1 | K11: 12689.05 | L11: =('Income Statement'!L6*Drivers!L14) -> 17572.302 | M11: =('Income Statement'!M6*Drivers!M14) -> 19860.216 | N11: =('Income Statement'!N6*Drivers!N14) -> 22733.989 | O11: =('Income Statement'!O6*Drivers!O14) -> 26100.893 | P11: =('Income Statement'!P6*Drivers!P14) -> 29256.491
A12: Investments | B12: 1161.36 | C12: 1078.92 | D12: 782.3 | E12: 1178 | F12: 2236.15 | G12: 3160.74 | H12: 7431.65 | I12: 4288.66 | J12: 4659.45 | K12: 5448.65 | L12: =K12 -> 5448.65 | M12: =L12 -> 5448.65 | N12: =M12 -> 5448.65 | O12: =N12 -> 5448.65 | P12: =O12 -> 5448.65
A13: Total assets | B13: =((((((B6+B7)+B8)+B9)+B10)+B11)+B12) -> 43369.37 | C13: =((((((C6+C7)+C8)+C9)+C10)+C11)+C12) -> 47232.72 | D13: =((((((D6+D7)+D8)+D9)+D10)+D11)+D12) -> 56311.43 | E13: =((((((E6+E7)+E8)+E9)+E10)+E11)+E12) -> 61916.7 | F13: =((((((F6+F7)+F8)+F9)+F10)+F11)+F12) -> 74581.93 | G13: =((((((G6+G7)+G8)+G9)+G10)+G11)+G12) -> 98327.99 | H13: =((((((H6+H7)+H8)+H9)+H10)+H11)+H12) -> 112563.19 | I13: =((((((I6+I7)+I8)+I9)+I10)+I11)+I12) -> 116999.2 | ... P13: =((((((P6+P7)+P8)+P9)+P10)+P11)+P12) -> 315238.2
A14: Liabilities and equity
A15: Share capital | B15: 414.19 | C15: 414.19 | D15: 414.19 | E15: 406.35 | F15: 406.35 | G15: 422.47 | H15: 432.03 | I15: 432.03 | J15: 432.03 | K15: 460.79 | L15: =K15 -> 460.79 | M15: =L15 -> 460.79 | N15: =M15 -> 460.79 | O15: =N15 -> 460.79 | P15: =O15 -> 460.79
A16: Reserves and surplus | B16: 17111.79 | C16: 20488.76 | D16: 23958.13 | E16: 25050.61 | F16: 30035.38 | G16: 41399.22 | H16: 44957.36 | I16: 52346.21 | J16: 61836.83 | K16: 95497.98 | L16: =(((K16+'Income Statement'!L18)-Schedules!L22)+Drivers!L27) -> 107236.87 | M16: =(((L16+'Income Statement'!M18)-Schedules!M22)+Drivers!M27) -> 120962.46 | N16: =(((M16+'Income Statement'!N18)-Schedules!N22)+Drivers!N27) -> 137256.72 | O16: =(((N16+'Income Statement'!O18)-Schedules!O22)+Drivers!O27) -> 156566.17 | P16: =(((O16+'Income Statement'!P18)-Schedules!P22)+Drivers!P27) -> 178512
A17: Term borrowings | B17: 22214.26 | C17: 22370.04 | D17: 27711.54 | E17: 30242.32 | F17: 35855.33 | G17: 47934.75 | H17: 53434.22 | I17: 49470.24 | J17: 51620.73 | K17: 63565.52 | L17: =MAX(((K17*(1+Drivers!L25))-Drivers!L26),0) -> 67817.672 | M17: =MAX(((L17*(1+Drivers!M25))-Drivers!M26),0) -> 72354.267 | N17: =MAX(((M17*(1+Drivers!N25))-Drivers!N26),0) -> 77194.334 | O17: =MAX(((N17*(1+Drivers!O25))-Drivers!O26),0) -> 82358.171 | P17: =MAX(((O17*(1+Drivers!P25))-Drivers!P26),0) -> 87867.439
A18: Revolver / short-term plug | B18: 0 | C18: 0 | D18: 0 | E18: 0 | F18: 0 | G18: 0 | H18: 0 | I18: 0 | J18: 0 | K18: 0 | L18: =((K18+Schedules!L18)-Schedules!L19) -> 0 | M18: =((L18+Schedules!M18)-Schedules!M19) -> 0 | N18: =((M18+Schedules!N18)-Schedules!N19) -> 0 | O18: =((N18+Schedules!O18)-Schedules!O19) -> 0 | P18: =((O18+Schedules!P18)-Schedules!P19) -> 0
A19: Total debt | B19: =(B17+B18) -> 22214.26 | C19: =(C17+C18) -> 22370.04 | D19: =(D17+D18) -> 27711.54 | E19: =(E17+E18) -> 30242.32 | F19: =(F17+F18) -> 35855.33 | G19: =(G17+G18) -> 47934.75 | H19: =(H17+H18) -> 53434.22 | I19: =(I17+I18) -> 49470.24 | ... P19: =(P17+P18) -> 87867.439
A20: Trade payables | B20: 0 | C20: 0 | D20: 0 | E20: 0 | F20: 0 | G20: 0 | H20: 0 | I20: 0 | J20: 2720.5 | K20: 2736.24 | L20: =(IFERROR((Drivers!L18)/(365),0)*'Income Statement'!L7) -> 3324.577 | M20: =(IFERROR((Drivers!M18)/(365),0)*'Income Statement'!M7) -> 3757.4369 | N20: =(IFERROR((Drivers!N18)/(365),0)*'Income Statement'!N7) -> 4301.1381 | O20: =(IFERROR((Drivers!O18)/(365),0)*'Income Statement'!O7) -> 4938.1366 | P20: =(IFERROR((Drivers!P18)/(365),0)*'Income Statement'!P7) -> 5535.1573
A21: Other liabilities | B21: 3629.13 | C21: 3959.73 | D21: 4227.57 | E21: 6217.42 | F21: 8284.87 | G21: 8571.55 | H21: 13739.58 | I21: 14750.72 | J21: 16832.56 | K21: 20838 | L21: =('Income Statement'!L6*Drivers!L20) -> 25744.66 | M21: =('Income Statement'!M6*Drivers!M20) -> 29096.615 | N21: =('Income Statement'!N6*Drivers!N20) -> 33306.895 | O21: =('Income Statement'!O6*Drivers!O20) -> 38239.646 | P21: =('Income Statement'!P6*Drivers!P20) -> 42862.819
A22: Total liabilities and equity | B22: =((((B15+B16)+B19)+B20)+B21) -> 43369.37 | C22: =((((C15+C16)+C19)+C20)+C21) -> 47232.72 | D22: =((((D15+D16)+D19)+D20)+D21) -> 56311.43 | E22: =((((E15+E16)+E19)+E20)+E21) -> 61916.7 | F22: =((((F15+F16)+F19)+F20)+F21) -> 74581.93 | G22: =((((G15+G16)+G19)+G20)+G21) -> 98327.99 | H22: =((((H15+H16)+H19)+H20)+H21) -> 112563.19 | I22: =((((I15+I16)+I19)+I20)+I21) -> 116999.2 | ... P22: =((((P15+P16)+P19)+P20)+P21) -> 315238.2

Sheet Cash Flow
A1: Adani Ports and Special Economic Zone Ltd - Cash Flow
A2: INR cr unless stated | built 2026-10-14 | blue = input, black = formula, green = link to another sheet
A4: Actuals | B4: Mar-17 | C4: Mar-18 | D4: Mar-19 | E4: Mar-20 | F4: Mar-21 | G4: Mar-22 | H4: Mar-23 | I4: Mar-24 | J4: Mar-25 | K4: Mar-26 | L4: Mar-27E | M4: Mar-28E | N4: Mar-29E | O4: Mar-30E | P4: Mar-31E
A5: Operating
A6: Profit after tax | B6: ='Income Statement'!B18 -> 3911.52 | C6: ='Income Statement'!C18 -> 3673.62 | D6: ='Income Statement'!D18 -> 3990.22 | E6: ='Income Statement'!E18 -> 3763.13 | F6: ='Income Statement'!F18 -> 4994.3 | G6: ='Income Statement'!G18 -> 4886.03 | H6: ='Income Statement'!H18 -> 5308.85 | I6: ='Income Statement'!I18 -> 8110.64 | ... P6: ='Income Statement'!P18 -> 25628.194
A7: Depreciation and amortisation | B7: ='Income Statement'!B11 -> 1160.19 | C7: ='Income Statement'!C11 -> 1188.37 | D7: ='Income Statement'!D11 -> 1373.48 | E7: ='Income Statement'!E11 -> 1680.28 | F7: ='Income Statement'!F11 -> 2107.34 | G7: ='Income Statement'!G11 -> 3099.3 | H7: ='Income Statement'!H11 -> 3424.71 | I7: ='Income Statement'!I11 -> 3888.46 | ... P7: ='Income Statement'!P11 -> 9623.2906
A8: (Increase)/decrease in net operating assets | B8: =-(Schedules!B12) -> -11034.61 | C8: =-(Schedules!C12) -> -976.44 | D8: =-(Schedules!D12) -> -718.31 | E8: =-(Schedules!E12) -> 1452.78 | F8: =-(Schedules!F12) -> 3904.54 | G8: =-(Schedules!G12) -> -1980.43 | H8: =-(Schedules!H12) -> 1155.32 | I8: =-(Schedules!I12) -> 3953.11 | ... P8: =-(Schedules!P12) -> -599.14606
A9: Cash from operations | B9: =((B6+B7)+B8) -> -5962.9 | C9: =((C6+C7)+C8) -> 3885.55 | D9: =((D6+D7)+D8) -> 4645.39 | E9: =((E6+E7)+E8) -> 6896.19 | F9: =((F6+F7)+F8) -> 11006.18 | G9: =((G6+G7)+G8) -> 6004.9 | H9: =((H6+H7)+H8) -> 9888.88 | I9: =((I6+I7)+I8) -> 15952.21 | ... P9: =((P6+P7)+P8) -> 34652.338
A10: Investing
A11: Capital expenditure | B11: =(-(Schedules!B7)-('Balance Sheet'!B11-0)) -> -4513.97 | C11: =(-(Schedules!C7)-('Balance Sheet'!C11-'Balance Sheet'!B11)) -> -2836.37 | D11: =(-(Schedules!D7)-('Balance Sheet'!D11-'Balance Sheet'!C11)) -> -6762.91 | E11: =(-(Schedules!E7)-('Balance Sheet'!E11-'Balance Sheet'!D11)) -> -5006.22 | F11: =(-(Schedules!F7)-('Balance Sheet'!F11-'Balance Sheet'!E11)) -> -18164.59 | G11: =(-(Schedules!G7)-('Balance Sheet'!G11-'Balance Sheet'!F11)) -> -17687.03 | H11: =(-(Schedules!H7)-('Balance Sheet'!H11-'Balance Sheet'!G11)) -> -15709.39 | I11: =(-(Schedules!I7)-('Balance Sheet'!I11-'Balance Sheet'!H11)) -> -11111.86 | J11: =(-(Schedules!J7)-('Balance Sheet'!J11-'Balance Sheet'!I11)) -> -19617.45 | ... P11: =(-(Schedules!P7)-('Balance Sheet'!P11-'Balance Sheet'!O11)) -> -23510.172
A12: Investments | B12: =-(('Balance Sheet'!B12-0)) -> -1161.36 | C12: =-(('Balance Sheet'!C12-'Balance Sheet'!B12)) -> 82.44 | D12: =-(('Balance Sheet'!D12-'Balance Sheet'!C12)) -> 296.62 | E12: =-(('Balance Sheet'!E12-'Balance Sheet'!D12)) -> -395.7 | F12: =-(('Balance Sheet'!F12-'Balance Sheet'!E12)) -> -1058.15 | G12: =-(('Balance Sheet'!G12-'Balance Sheet'!F12)) -> -924.59 | H12: =-(('Balance Sheet'!H12-'Balance Sheet'!G12)) -> -4270.91 | I12: =-(('Balance Sheet'!I12-'Balance Sheet'!H12)) -> 3142.99 | J12: =-(('Balance Sheet'!J12-'Balance Sheet'!I12)) -> -370.79 | ... P12: =-(('Balance Sheet'!P12-'Balance Sheet'!O12)) -> 0
A13: Cash from investing | B13: =(B11+B12) -> -5675.33 | C13: =(C11+C12) -> -2753.93 | D13: =(D11+D12) -> -6466.29 | E13: =(E11+E12) -> -5401.92 | F13: =(F11+F12) -> -19222.74 | G13: =(G11+G12) -> -18611.62 | H13: =(H11+H12) -> -19980.3 | I13: =(I11+I12) -> -7968.87 | ... P13: =(P11+P12) -> -23510.172
A14: Financing
A15: Term debt drawn/(repaid) | B15: =('Balance Sheet'!B17-0) -> 22214.26 | C15: =('Balance Sheet'!C17-'Balance Sheet'!B17) -> 155.78 | D15: =('Balance Sheet'!D17-'Balance Sheet'!C17) -> 5341.5 | E15: =('Balance Sheet'!E17-'Balance Sheet'!D17) -> 2530.78 | F15: =('Balance Sheet'!F17-'Balance Sheet'!E17) -> 5613.01 | G15: =('Balance Sheet'!G17-'Balance Sheet'!F17) -> 12079.42 | H15: =('Balance Sheet'!H17-'Balance Sheet'!G17) -> 5499.47 | I15: =('Balance Sheet'!I17-'Balance Sheet'!H17) -> -3963.98 | J15: =('Balance Sheet'!J17-'Balance Sheet'!I17) -> 2150.49 | ... P15: =('Balance Sheet'!P17-'Balance Sheet'!O17) -> 5509.2675
A16: Revolver drawn/(repaid) | B16: =('Balance Sheet'!B18-0) -> 0 | C16: =('Balance Sheet'!C18-'Balance Sheet'!B18) -> 0 | D16: =('Balance Sheet'!D18-'Balance Sheet'!C18) -> 0 | E16: =('Balance Sheet'!E18-'Balance Sheet'!D18) -> 0 | F16: =('Balance Sheet'!F18-'Balance Sheet'!E18) -> 0 | G16: =('Balance Sheet'!G18-'Balance Sheet'!F18) -> 0 | H16: =('Balance Sheet'!H18-'Balance Sheet'!G18) -> 0 | I16: =('Balance Sheet'!I18-'Balance Sheet'!H18) -> 0 | J16: =('Balance Sheet'!J18-'Balance Sheet'!I18) -> 0 | ... P16: =('Balance Sheet'!P18-'Balance Sheet'!O18) -> 0
A17: Dividends paid | B17: =-(Schedules!B22) -> -269.22 | C17: =-(Schedules!C22) -> -414.19 | D17: =-(Schedules!D22) -> -41.42 | E17: =-(Schedules!E22) -> -650.16 | F17: =-(Schedules!F22) -> -1015.88 | G17: =-(Schedules!G22) -> -1056.18 | H17: =-(Schedules!H22) -> -1080.08 | I17: =-(Schedules!I22) -> -1296.09 | ... P17: =-(Schedules!P22) -> -3682.3614
A18: Equity issued | B18: =Drivers!B27 -> 0 | C18: =Drivers!C27 -> 0 | D18: =Drivers!D27 -> 0 | E18: =Drivers!E27 -> 0 | F18: =Drivers!F27 -> 0 | G18: =Drivers!G27 -> 0 | H18: =Drivers!H27 -> 0 | I18: =Drivers!I27 -> 0 | ... P18: =Drivers!P27 -> 0
A19: Cash from financing | B19: =(((B15+B16)+B17)+B18) -> 21945.04 | C19: =(((C15+C16)+C17)+C18) -> -258.41 | D19: =(((D15+D16)+D17)+D18) -> 5300.08 | E19: =(((E15+E16)+E17)+E18) -> 1880.62 | F19: =(((F15+F16)+F17)+F18) -> 4597.13 | G19: =(((G15+G16)+G17)+G18) -> 11023.24 | H19: =(((H15+H16)+H17)+H18) -> 4419.39 | I19: =(((I15+I16)+I17)+I18) -> -5260.07 | ... P19: =(((P15+P16)+P17)+P18) -> 1826.9061
A20: Cash reconciliation
A21: Net change in cash | B21: =((B9+B13)+B19) -> 10306.81 | C21: =((C9+C13)+C19) -> 873.21 | D21: =((D9+D13)+D19) -> 3479.18 | E21: =((E9+E13)+E19) -> 3374.89 | F21: =((F9+F13)+F19) -> -3619.43 | G21: =((G9+G13)+G19) -> -1583.48 | H21: =((H9+H13)+H19) -> -5672.03 | I21: =((I9+I13)+I19) -> 2723.27 | ... P21: =((P9+P13)+P19) -> 12969.072
A22: Opening cash | B22: =0 -> 0 | C22: ='Balance Sheet'!B6 -> 1976.8 | D22: ='Balance Sheet'!C6 -> 2967.55 | E22: ='Balance Sheet'!D6 -> 5967.3 | F22: ='Balance Sheet'!E6 -> 7313.86 | G22: ='Balance Sheet'!F6 -> 4700.78 | H22: ='Balance Sheet'!G6 -> 10667.41 | I22: ='Balance Sheet'!H6 -> 4334.31 | J22: ='Balance Sheet'!I6 -> 7631.88 | ... P22: ='Balance Sheet'!O6 -> 36651.537
A23: Closing cash | B23: =(B22+B21) -> 10306.81 | C23: =(C22+C21) -> 2850.01 | D23: =(D22+D21) -> 6446.73 | E23: =(E22+E21) -> 9342.19 | F23: =(F22+F21) -> 3694.43 | G23: =(G22+G21) -> 3117.3 | H23: =(H22+H21) -> 4995.38 | I23: =(I22+I21) -> 7057.58 | ... P23: =(P22+P21) -> 49620.609
A24: Reported cash flow (history only)
A25: Reported cash from operations | B25: 4062.57 | C25: 5608.14 | D25: 6029.4 | E25: 7401.81 | F25: 7555.78 | G25: 10420.14 | H25: 11899.5 | I25: 15017.58 | J25: 17226.28 | K25: 20356.25 | L25: =0 -> 0 | M25: =0 -> 0 | N25: =0 -> 0 | O25: =0 -> 0 | P25: =0 -> 0
A26: Reported cash from investing | B26: -2629.15 | C26: -3845.84 | D26: -4368.03 | E26: -748.91 | F26: -14064.12 | G26: -5493.13 | H26: -16715.93 | I26: -6946.55 | J26: -9787.53 | K26: -13190.7 | L26: =0 -> 0 | M26: =0 -> 0 | N26: =0 -> 0 | O26: =0 -> 0 | P26: =0 -> 0
A27: Reported cash from financing | B27: -1324.71 | C27: -1889.03 | D27: 2313.34 | E27: -4255.63 | F27: 3513.85 | G27: -585.77 | H27: -2733.8 | I27: -7800.11 | J27: -6915.52 | K27: -5483.4 | L27: =0 -> 0 | M27: =0 -> 0 | N27: =0 -> 0 | O27: =0 -> 0 | P27: =0 -> 0
A28: Reconstructed less reported CFO | B28: =(B9-B25) -> -10025.47 | C28: =(C9-C25) -> -1722.59 | D28: =(D9-D25) -> -1384.01 | E28: =(E9-E25) -> -505.62 | F28: =(F9-F25) -> 3450.4 | G28: =(G9-G25) -> -4415.24 | H28: =(H9-H25) -> -2010.62 | I28: =(I9-I25) -> 934.63 | ... P28: =(P9-P25) -> 34652.338

Sheet Schedules
A1: Adani Ports and Special Economic Zone Ltd - Schedules
A2: INR cr unless stated | built 2026-10-14 | blue = input, black = formula, green = link to another sheet
A4: Actuals | B4: Mar-17 | C4: Mar-18 | D4: Mar-19 | E4: Mar-20 | F4: Mar-21 | G4: Mar-22 | H4: Mar-23 | I4: Mar-24 | J4: Mar-25 | K4: Mar-26 | L4: Mar-27E | M4: Mar-28E | N4: Mar-29E | O4: Mar-30E | P4: Mar-31E
A5: Fixed assets
A6: Opening net block | B6: =0 -> 0 | C6: ='Balance Sheet'!B10 -> 21053.5 | D6: ='Balance Sheet'!C10 -> 22670.01 | E6: ='Balance Sheet'!D10 -> 28121.42 | F6: ='Balance Sheet'!E10 -> 32714.51 | G6: ='Balance Sheet'!F10 -> 48290.96 | H6: ='Balance Sheet'!G10 -> 62552.92 | I6: ='Balance Sheet'!H10 -> 72223.73 | J6: ='Balance Sheet'!I10 -> 75147.81 | ... P6: ='Balance Sheet'!O10 -> 166228.33
A7: Capital expenditure | B7: 0 | C7: 2804.88 | D7: 6824.89 | E7: 6273.37 | F7: 17683.79 | G7: 17361.26 | H7: 13095.52 | I7: 6812.54 | J7: 18847.44 | K7: 47553.56 | L7: =('Income Statement'!L6*Drivers!L11) -> 14576.619 | M7: =('Income Statement'!M6*Drivers!M11) -> 15943.059 | N7: =('Income Statement'!N6*Drivers!N11) -> 17641.686 | O7: =('Income Statement'!O6*Drivers!O11) -> 19555.991 | P7: =('Income Statement'!P6*Drivers!P11) -> 20354.574
A8: Depreciation charge | B8: ='Income Statement'!B11 -> 1160.19 | C8: ='Income Statement'!C11 -> 1188.37 | D8: ='Income Statement'!D11 -> 1373.48 | E8: ='Income Statement'!E11 -> 1680.28 | F8: ='Income Statement'!F11 -> 2107.34 | G8: ='Income Statement'!G11 -> 3099.3 | H8: ='Income Statement'!H11 -> 3424.71 | I8: ='Income Statement'!I11 -> 3888.46 | ... P8: ='Income Statement'!P11 -> 9623.2906
A9: Closing net block | B9: =((B6+B7)-B8) -> -1160.19 | C9: =((C6+C7)-C8) -> 22670.01 | D9: =((D6+D7)-D8) -> 28121.42 | E9: =((E6+E7)-E8) -> 32714.51 | F9: =((F6+F7)-F8) -> 48290.96 | G9: =((G6+G7)-G8) -> 62552.92 | H9: =((H6+H7)-H8) -> 72223.73 | I9: =((I6+I7)-I8) -> 75147.81 | ... P9: =((P6+P7)-P8) -> 176959.62
A10: Working capital
A11: Net operating assets | B11: =(((('Balance Sheet'!B7+'Balance Sheet'!B8)+'Balance Sheet'!B9)-'Balance Sheet'!B20)-'Balance Sheet'!B21) -> 11034.61 | C11: =(((('Balance Sheet'!C7+'Balance Sheet'!C8)+'Balance Sheet'!C9)-'Balance Sheet'!C20)-'Balance Sheet'!C21) -> 12011.05 | D11: =(((('Balance Sheet'!D7+'Balance Sheet'!D8)+'Balance Sheet'!D9)-'Balance Sheet'!D20)-'Balance Sheet'!D21) -> 12729.36 | E11: =(((('Balance Sheet'!E7+'Balance Sheet'!E8)+'Balance Sheet'!E9)-'Balance Sheet'!E20)-'Balance Sheet'!E21) -> 11276.58 | F11: =(((('Balance Sheet'!F7+'Balance Sheet'!F8)+'Balance Sheet'!F9)-'Balance Sheet'!F20)-'Balance Sheet'!F21) -> 7372.04 | G11: =(((('Balance Sheet'!G7+'Balance Sheet'!G8)+'Balance Sheet'!G9)-'Balance Sheet'!G20)-'Balance Sheet'!G21) -> 9352.47 | H11: =(((('Balance Sheet'!H7+'Balance Sheet'!H8)+'Balance Sheet'!H9)-'Balance Sheet'!H20)-'Balance Sheet'!H21) -> 8197.15 | I11: =(((('Balance Sheet'!I7+'Balance Sheet'!I8)+'Balance Sheet'!I9)-'Balance Sheet'!I20)-'Balance Sheet'!I21) -> 4244.04 | ... P11: =(((('Balance Sheet'!P7+'Balance Sheet'!P8)+'Balance Sheet'!P9)-'Balance Sheet'!P20)-'Balance Sheet'!P21) -> 5554.862
A12: Change in net operating assets | B12: =(B11-0) -> 11034.61 | C12: =(C11-B11) -> 976.44 | D12: =(D11-C11) -> 718.31 | E12: =(E11-D11) -> -1452.78 | F12: =(F11-E11) -> -3904.54 | G12: =(G11-F11) -> 1980.43 | H12: =(H11-G11) -> -1155.32 | I12: =(I11-H11) -> -3953.11 | J12: =(J11-I11) -> -2942.29 | ... P12: =(P11-O11) -> 599.14606
A13: Net operating assets (days of sales) | B13: =(IFERROR((B11)/('Income Statement'!B6),0)*365) -> 477.24441 | C13: =(IFERROR((C11)/('Income Statement'!C6),0)*365) -> 387.18085 | D13: =(IFERROR((D11)/('Income Statement'!D6),0)*365) -> 425.26584 | E13: =(IFERROR((E11)/('Income Statement'!E6),0)*365) -> 346.6628 | F13: =(IFERROR((F11)/('Income Statement'!F6),0)*365) -> 214.41278 | G13: =(IFERROR((G11)/('Income Statement'!G6),0)*365) -> 199.40963 | H13: =(IFERROR((H11)/('Income Statement'!H6),0)*365) -> 143.48612 | I13: =(IFERROR((I11)/('Income Statement'!I6),0)*365) -> 57.994838 | ... P13: =(IFERROR((P11)/('Income Statement'!P6),0)*365) -> 25.89867
A14: Debt, revolver and interest
A15: Opening term debt | B15: =0 -> 0 | C15: ='Balance Sheet'!B17 -> 22214.26 | D15: ='Balance Sheet'!C17 -> 22370.04 | E15: ='Balance Sheet'!D17 -> 27711.54 | F15: ='Balance Sheet'!E17 -> 30242.32 | G15: ='Balance Sheet'!F17 -> 35855.33 | H15: ='Balance Sheet'!G17 -> 47934.75 | I15: ='Balance Sheet'!H17 -> 53434.22 | J15: ='Balance Sheet'!I17 -> 49470.24 | ... P15: ='Balance Sheet'!O17 -> 82358.171
A16: Financing flows before the revolver | B16: =(('Cash Flow'!B15+'Cash Flow'!B17)+'Cash Flow'!B18) -> 21945.04 | C16: =(('Cash Flow'!C15+'Cash Flow'!C17)+'Cash Flow'!C18) -> -258.41 | D16: =(('Cash Flow'!D15+'Cash Flow'!D17)+'Cash Flow'!D18) -> 5300.08 | E16: =(('Cash Flow'!E15+'Cash Flow'!E17)+'Cash Flow'!E18) -> 1880.62 | F16: =(('Cash Flow'!F15+'Cash Flow'!F17)+'Cash Flow'!F18) -> 4597.13 | G16: =(('Cash Flow'!G15+'Cash Flow'!G17)+'Cash Flow'!G18) -> 11023.24 | H16: =(('Cash Flow'!H15+'Cash Flow'!H17)+'Cash Flow'!H18) -> 4419.39 | I16: =(('Cash Flow'!I15+'Cash Flow'!I17)+'Cash Flow'!I18) -> -5260.07 | ... P16: =(('Cash Flow'!P15+'Cash Flow'!P17)+'Cash Flow'!P18) -> 1826.9061
A17: Cash before the revolver | B17: =(((0+'Cash Flow'!B9)+'Cash Flow'!B13)+B16) -> 10306.81 | C17: =((('Balance Sheet'!B6+'Cash Flow'!C9)+'Cash Flow'!C13)+C16) -> 2850.01 | D17: =((('Balance Sheet'!C6+'Cash Flow'!D9)+'Cash Flow'!D13)+D16) -> 6446.73 | E17: =((('Balance Sheet'!D6+'Cash Flow'!E9)+'Cash Flow'!E13)+E16) -> 9342.19 | F17: =((('Balance Sheet'!E6+'Cash Flow'!F9)+'Cash Flow'!F13)+F16) -> 3694.43 | G17: =((('Balance Sheet'!F6+'Cash Flow'!G9)+'Cash Flow'!G13)+G16) -> 3117.3 | H17: =((('Balance Sheet'!G6+'Cash Flow'!H9)+'Cash Flow'!H13)+H16) -> 4995.38 | I17: =((('Balance Sheet'!H6+'Cash Flow'!I9)+'Cash Flow'!I13)+I16) -> 7057.58 | J17: =((('Balance Sheet'!I6+'Cash Flow'!J9)+'Cash Flow'!J13)+J16) -> 6695.56 | ... P17: =((('Balance Sheet'!O6+'Cash Flow'!P9)+'Cash Flow'!P13)+P16) -> 49620.609
A18: Revolver drawn | B18: =MAX((Drivers!B29-B17),0) -> 0 | C18: =MAX((Drivers!C29-C17),0) -> 0 | D18: =MAX((Drivers!D29-D17),0) -> 0 | E18: =MAX((Drivers!E29-E17),0) -> 0 | F18: =MAX((Drivers!F29-F17),0) -> 0 | G18: =MAX((Drivers!G29-G17),0) -> 0 | H18: =MAX((Drivers!H29-H17),0) -> 0 | I18: =MAX((Drivers!I29-I17),0) -> 0 | ... P18: =MAX((Drivers!P29-P17),0) -> 0
A19: Revolver repaid | B19: =MIN(0,MAX((B17-Drivers!B29),0)) -> 0 | C19: =MIN('Balance Sheet'!B18,MAX((C17-Drivers!C29),0)) -> 0 | D19: =MIN('Balance Sheet'!C18,MAX((D17-Drivers!D29),0)) -> 0 | E19: =MIN('Balance Sheet'!D18,MAX((E17-Drivers!E29),0)) -> 0 | F19: =MIN('Balance Sheet'!E18,MAX((F17-Drivers!F29),0)) -> 0 | G19: =MIN('Balance Sheet'!F18,MAX((G17-Drivers!G29),0)) -> 0 | H19: =MIN('Balance Sheet'!G18,MAX((H17-Drivers!H29),0)) -> 0 | I19: =MIN('Balance Sheet'!H18,MAX((I17-Drivers!I29),0)) -> 0 | J19: =MIN('Balance Sheet'!I18,MAX((J17-Drivers!J29),0)) -> 0 | ... P19: =MIN('Balance Sheet'!O18,MAX((P17-Drivers!P29),0)) -> 0
A20: Average total debt | B20: =AVERAGE(0,'Balance Sheet'!B19) -> 11107.13 | C20: =AVERAGE('Balance Sheet'!B19,'Balance Sheet'!C19) -> 22292.15 | D20: =AVERAGE('Balance Sheet'!C19,'Balance Sheet'!D19) -> 25040.79 | E20: =AVERAGE('Balance Sheet'!D19,'Balance Sheet'!E19) -> 28976.93 | F20: =AVERAGE('Balance Sheet'!E19,'Balance Sheet'!F19) -> 33048.825 | G20: =AVERAGE('Balance Sheet'!F19,'Balance Sheet'!G19) -> 41895.04 | H20: =AVERAGE('Balance Sheet'!G19,'Balance Sheet'!H19) -> 50684.485 | I20: =AVERAGE('Balance Sheet'!H19,'Balance Sheet'!I19) -> 51452.23 | J20: =AVERAGE('Balance Sheet'!I19,'Balance Sheet'!J19) -> 50545.485 | ... P20: =AVERAGE('Balance Sheet'!O19,'Balance Sheet'!P19) -> 85112.805
A21: Equity and shareholders
A22: Dividends declared | B22: 269.22 | C22: 414.19 | D22: 41.42 | E22: 650.16 | F22: 1015.88 | G22: 1056.18 | H22: 1080.08 | I22: 1296.09 | J22: 1512.1 | K22: 1727.96 | L22: =('Income Statement'!L18*Drivers!L28) -> 1969.7064 | M22: =('Income Statement'!M18*Drivers!M28) -> 2303.0603 | N22: =('Income Statement'!N18*Drivers!N28) -> 2734.0653 | O22: =('Income Statement'!O18*Drivers!O28) -> 3239.9943 | P22: =('Income Statement'!P18*Drivers!P28) -> 3682.3614
A23: Shares outstanding | B23: 207.0952 | C23: 207.0952 | D23: 207.0952 | E23: 203.1752 | F23: 203.1752 | G23: 211.2373 | H23: 216.0139 | I23: 216.0139 | J23: 216.0139 | K23: 230.3959 | L23: =K23 -> 230.3959 | M23: =L23 -> 230.3959 | N23: =M23 -> 230.3959 | O23: =N23 -> 230.3959 | P23: =O23 -> 230.3959
A24: Shareholders' equity | B24: =('Balance Sheet'!B15+'Balance Sheet'!B16) -> 17525.98 | C24: =('Balance Sheet'!C15+'Balance Sheet'!C16) -> 20902.95 | D24: =('Balance Sheet'!D15+'Balance Sheet'!D16) -> 24372.32 | E24: =('Balance Sheet'!E15+'Balance Sheet'!E16) -> 25456.96 | F24: =('Balance Sheet'!F15+'Balance Sheet'!F16) -> 30441.73 | G24: =('Balance Sheet'!G15+'Balance Sheet'!G16) -> 41821.69 | H24: =('Balance Sheet'!H15+'Balance Sheet'!H16) -> 45389.39 | I24: =('Balance Sheet'!I15+'Balance Sheet'!I16) -> 52778.24 | ... P24: =('Balance Sheet'!P15+'Balance Sheet'!P16) -> 178972.79
A25: Book value per share | B25: =IFERROR((B24)/(B23),0) -> 84.62765 | C25: =IFERROR((C24)/(C23),0) -> 100.93401 | D25: =IFERROR((D24)/(D23),0) -> 117.68655 | E25: =IFERROR((E24)/(E23),0) -> 125.29561 | F25: =IFERROR((F24)/(F23),0) -> 149.82995 | G25: =IFERROR((G24)/(G23),0) -> 197.9844 | H25: =IFERROR((H24)/(H23),0) -> 210.12254 | I25: =IFERROR((I24)/(I23),0) -> 244.32798 | ... P25: =IFERROR((P24)/(P23),0) -> 776.80544

Sheet WACC
A1: Adani Ports and Special Economic Zone Ltd - Cost of capital
A2: CAPM cost of equity, post-tax cost of debt, target weights
B4: Value | C4: Basis
A5: Cost of equity
A6: Risk-free rate | B6: 0.0678 | C6: 10-year G-sec yield (assumptions.json)
A7: Equity risk premium | B7: 0.055 | C7: assumptions.json
A8: Raw beta | B8: 1.3 | C8: assumptions.json
A9: Blume-adjusted beta (0.67 x beta + 0.33) | B9: =0.67*B8+0.33 -> 1.201
A10: Cost of equity (CAPM) | B10: =B6+B9*B7 -> 0.133855
A12: Cost of debt and weights
A13: Pre-tax cost of debt | B13: 0.08 | C13: assumptions.json
A14: Tax rate (active scenario, first forecast year) | B14: =Scenarios!B39 -> 0.185 | C14: Scenarios sheet
A15: Post-tax cost of debt | B15: =B13*(1-B14) -> 0.0652
A16: Target debt weight | B16: 0.12 | C16: assumptions.json
A18: WACC | B18: =B10*(1-B16)+B15*B16 -> 0.1256164
A19: Terminal growth (active scenario) | B19: =Scenarios!$B$40 -> 0.05
A20: Terminal growth below WACC | B20: =IF(B19<WACC!$B$18,"OK","FAIL") -> OK

Sheet DCF
A1: Adani Ports and Special Economic Zone Ltd - DCF
A2: FCFF from the linked statements; stub-period discounting from the balance-sheet date; exit-multiple target
A4: INR cr unless stated | B4: Mar-27E | C4: Mar-28E | D4: Mar-29E | E4: Mar-30E | F4: Mar-31E
A5: Free cash flow to the firm
A6: Revenue | B6: ='Income Statement'!L6 -> 47021.351 | C6: ='Income Statement'!M6 -> 53143.531 | D6: ='Income Statement'!N6 -> 60833.4 | E6: ='Income Statement'!O6 -> 69842.827 | F6: ='Income Statement'!P6 -> 78286.824
A7: EBITDA | B7: ='Income Statement'!L10 -> 27507.49 | C7: ='Income Statement'!M10 -> 30823.248 | D7: ='Income Statement'!N10 -> 34979.205 | E7: ='Income Statement'!O10 -> 39810.411 | F7: ='Income Statement'!P10 -> 44232.056
A8: EBIT | B8: ='Income Statement'!L12 -> 19885.864 | C8: ='Income Statement'!M12 -> 22798.983 | D8: ='Income Statement'!N12 -> 26496.505 | E8: ='Income Statement'!O12 -> 30797.479 | F8: ='Income Statement'!P12 -> 34608.765
A9: Tax rate | B9: =Drivers!L22 -> 0.185 | C9: =Drivers!M22 -> 0.185 | D9: =Drivers!N22 -> 0.185 | E9: =Drivers!O22 -> 0.185 | F9: =Drivers!P22 -> 0.185
A10: NOPAT (EBIT x (1 - tax rate)) | B10: =B8*(1-B9) -> 16206.979 | C10: =C8*(1-C9) -> 18581.171 | D10: =D8*(1-D9) -> 21594.652 | E10: =E8*(1-E9) -> 25099.946 | F10: =F8*(1-F9) -> 28206.144
A11: Add: depreciation and amortisation | B11: ='Income Statement'!L11 -> 7621.6265 | C11: ='Income Statement'!M11 -> 8024.2649 | D11: ='Income Statement'!N11 -> 8482.6998 | E11: ='Income Statement'!O11 -> 9012.9318 | F11: ='Income Statement'!P11 -> 9623.2906
A12: Less: capital expenditure | B12: =-Schedules!L7 -> -14576.619 | C12: =-Schedules!M7 -> -15943.059 | D12: =-Schedules!N7 -> -17641.686 | E12: =-Schedules!O7 -> -19555.991 | F12: =-Schedules!P7 -> -20354.574
A13: Less: increase in net operating assets | B13: =-Schedules!L12 -> -2085.8322 | C13: =-Schedules!M12 -> -434.40087 | D13: =-Schedules!N12 -> -545.63665 | E13: =-Schedules!O12 -> -639.26621 | F13: =-Schedules!P12 -> -599.14606
A14: Free cash flow to the firm | B14: =B10+B11+B12+B13 -> 7166.1545 | C14: =C10+C11+C12+C13 -> 10227.976 | D14: =D10+D11+D12+D13 -> 11890.029 | E14: =E10+E11+E12+E13 -> 13917.62 | F14: =F10+F11+F12+F13 -> 16875.714
A16: Timing and discounting
A17: Balance-sheet date (date of the net debt) | B17: 46112 | C17: Cash flows before it are inside net debt
A18: First forecast year ends | B18: 46477
A19: Valuation date (cover) | B19: 46241
A20: Share of the first year counted (stub) | B20: =MIN(1,MAX(0,(B18-B17)/365.25)) -> 0.99931554
A21: Share of year counted | B21: =$B$20 -> 0.99931554 | C21: 1 | D21: 1 | E21: 1 | F21: 1
A22: Discount period (years from balance-sheet date, mid-year) | B22: =$B$20*0.5 -> 0.49965777 | C22: =$B$20+0.5 -> 1.4993155 | D22: =C22+1 -> 2.4993155 | E22: =D22+1 -> 3.4993155 | F22: =E22+1 -> 4.4993155
A23: Discount factor | B23: =1/(1+WACC!$B$18)^B22 -> 0.94258903 | C23: =1/(1+WACC!$B$18)^C22 -> 0.83743201 | D23: =1/(1+WACC!$B$18)^D22 -> 0.74397637 | E23: =1/(1+WACC!$B$18)^E22 -> 0.66095019 | F23: =1/(1+WACC!$B$18)^F22 -> 0.58718955
A24: Present value of FCFF | B24: =B14*B21*B23 -> 6750.1153 | C24: =C14*C21*C23 -> 8565.2345 | D24: =D14*D21*D23 -> 8845.9006 | E24: =E14*E21*E23 -> 9198.8535 | F24: =F14*F21*F23 -> 9909.2429
A26: Valuation: perpetuity
A27: WACC | B27: =WACC!$B$18 -> 0.1256164
A28: Terminal growth (active scenario) | B28: =Scenarios!$B$40 -> 0.05
A29: Return on new invested capital in perpetuity (RONIC) | B29: 0.105 | C29: assumptions.json terminal_ronic
A30: Terminal reinvestment rate (g / RONIC, share of NOPAT) | B30: =$B$28/$B$29 -> 0.47619048
A31: Sum of PV of FCFF | B31: =SUM(B24:F24) -> 43269.347
A32: Terminal value (NOPAT N x (1 + g) x (1 - g / RONIC) / (WACC - g)) | B32: =F10*(1+$B$28)*(1-$B$28/$B$29)/($B$27-$B$28) -> 205158.92
A33: PV of terminal value (at the final cash flow's period) | B33: =$B$32/(1+$B$27)^F22 -> 120467.17
A34: Enterprise value | B34: =$B$31+$B$33 -> 163736.52
A35: Terminal value as % of EV | B35: =$B$33/$B$34 -> 0.73573796
A36: Net debt at the balance-sheet date (negative = net cash) | B36: 42910 | C36: assumptions.json net_debt, as at the balance-sheet date
A37: Lease liabilities (Ind AS 116, debt-like) | B37: 8296.02 | C37: assumptions.json lease_liabilities (annual report)
A38: Minority interest (book value) | B38: 2856.18 | C38: assumptions.json minority_interest (annual report)
A39: Non-operating assets | B39: 3340.86 | C39: Treasury investments and stakes not in FCFF
A40: Equity value at the balance-sheet date | B40: =$B$34-$B$36-$B$37-$B$38+$B$39 -> 113015.18
A41: Cost of equity | B41: =WACC!$B$10 -> 0.133855
A42: Roll-forward to the valuation date ((1 + ke) ^ years) | B42: =(1+$B$41)^((B19-B17)/365.25) -> 1.045367
A43: Equity value at the valuation date | B43: =$B$40*$B$42 -> 118142.34
A44: Shares outstanding (Cr) | B44: =Schedules!K23 -> 230.3959
A45: Value per share, perpetuity (INR) | B45: =$B$43/$B$44 -> 512.77969
A46: Current market price (INR) | B46: 1695 | C46: NSE close, 7 Aug 2026 (cover date)
A47: Upside / (downside) | B47: =$B$45/$B$46-1 -> -0.69747511
A49: Target price (12-month forward)
A50: Target method (Perpetuity DCF or Exit multiple) | B50: Perpetuity DCF | C50: assumptions.json target_policy
A51: Horizon (months) | B51: 12
A52: Value per share today, on the target method | B52: =IF($B$50="Exit multiple",$B$68,$B$45) -> 512.77969
A53: Dividend per share, next 12 months (first forecast year) | B53: =IFERROR(Schedules!L22/Schedules!L23,0) -> 8.5492252 | C53: Schedules: dividends declared / shares, first forecast year
A54: Forward value (value x (1 + ke)^(h/12) - DPS x h/12) | B54: =$B$52*(1+$B$41)^($B$51/12)-$B$53*$B$51/12 -> 572.86859
A55: Rounding step (INR) | B55: 5
A56: Target price (INR) | B56: =ROUND($B$54/$B$55,0)*$B$55 -> 575
A57: Upside / (downside) to target | B57: =$B$56/$B$46-1 -> -0.66076696
A58: BUY above | B58: 0.15 | C58: House rating policy
A59: SELL below | B59: -0.1 | C59: House rating policy
A60: Rating | B60: =IF($B$57>$B$58,"BUY",IF($B$57<$B$59,"SELL","HOLD")) -> SELL
A62: Exit-multiple cross-check (not the target unless chosen above)
A63: Terminal-year EBITDA | B63: =F7 -> 44232.056
A64: Exit EV/EBITDA implied by the perpetuity TV | B64: =$B$32/$B$63 -> 4.6382407
A65: Exit multiple | B65: 10
A66: Terminal value at exit multiple | B66: =$B$65*$B$63 -> 442320.56
A67: PV of exit terminal value | B67: =$B$66/(1+$B$27)^F22 -> 259726.01
A68: Value per share at exit multiple (INR) | B68: =($B$31+$B$67-$B$36-$B$37-$B$38+$B$39)*$B$42/$B$44 -> 1144.6338
A69: Alternative exit multiple | B69: 14 | C69: Cross-check (assumptions.json exit_multiple)
A70: Value per share at alternative exit (INR) | B70: =($B$31+$B$69*$B$63/(1+$B$27)^F22-$B$36-$B$37-$B$38+$B$39)*$B$42/$B$44 -> 1616.0119

Sheet Sensitivity
A1: Adani Ports and Special Economic Zone Ltd - Sensitivity
A2: Value per share (INR); every cell recomputes the DCF from the FCFF row
A4: Step (WACC and growth) | B4: 0.005
A5: Step (exit multiple) | B5: 2
A7: WACC x terminal growth (perpetuity value per share)
A8: WACC ↓ / terminal growth → | B8: =DCF!$B$28+(-2)*$B$4 -> 0.04 | C8: =DCF!$B$28+(-1)*$B$4 -> 0.045 | D8: =DCF!$B$28+(0)*$B$4 -> 0.05 | E8: =DCF!$B$28+(1)*$B$4 -> 0.055 | F8: =DCF!$B$28+(2)*$B$4 -> 0.06
A9: =DCF!$B$27+(-2)*$B$4 -> 0.1156164 | B9: =IF(B$8>=$A9,NA(),(SUMPRODUCT(DCF!$B$14:$F$14,DCF!$B$21:$F$21,1/(1+$A9)^DCF!$B$22:$F$22)+DCF!$F$10*(1+B$8)*(1-B$8/DCF!$B$29)/($A9-B$8)/(1+$A9)^DCF!$F$22-DCF!$B$36-DCF!$B$37-DCF!$B$38+DCF!$B$39)*DCF!$B$42/DCF!$B$44) -> 636.95105 | C9: =IF(C$8>=$A9,NA(),(SUMPRODUCT(DCF!$B$14:$F$14,DCF!$B$21:$F$21,1/(1+$A9)^DCF!$B$22:$F$22)+DCF!$F$10*(1+C$8)*(1-C$8/DCF!$B$29)/($A9-C$8)/(1+$A9)^DCF!$F$22-DCF!$B$36-DCF!$B$37-DCF!$B$38+DCF!$B$39)*DCF!$B$42/DCF!$B$44) -> 632.41375 | D9: =IF(D$8>=$A9,NA(),(SUMPRODUCT(DCF!$B$14:$F$14,DCF!$B$21:$F$21,1/(1+$A9)^DCF!$B$22:$F$22)+DCF!$F$10*(1+D$8)*(1-D$8/DCF!$B$29)/($A9-D$8)/(1+$A9)^DCF!$F$22-DCF!$B$36-DCF!$B$37-DCF!$B$38+DCF!$B$39)*DCF!$B$42/DCF!$B$44) -> 626.61725 | E9: =IF(E$8>=$A9,NA(),(SUMPRODUCT(DCF!$B$14:$F$14,DCF!$B$21:$F$21,1/(1+$A9)^DCF!$B$22:$F$22)+DCF!$F$10*(1+E$8)*(1-E$8/DCF!$B$29)/($A9-E$8)/(1+$A9)^DCF!$F$22-DCF!$B$36-DCF!$B$37-DCF!$B$38+DCF!$B$39)*DCF!$B$42/DCF!$B$44) -> 619.24997 | F9: =IF(F$8>=$A9,NA(),(SUMPRODUCT(DCF!$B$14:$F$14,DCF!$B$21:$F$21,1/(1+$A9)^DCF!$B$22:$F$22)+DCF!$F$10*(1+F$8)*(1-F$8/DCF!$B$29)/($A9-F$8)/(1+$A9)^DCF!$F$22-DCF!$B$36-DCF!$B$37-DCF!$B$38+DCF!$B$39)*DCF!$B$42/DCF!$B$44) -> 609.88824
A10: =DCF!$B$27+(-1)*$B$4 -> 0.1206164 | B10: =IF(B$8>=$A10,NA(),(SUMPRODUCT(DCF!$B$14:$F$14,DCF!$B$21:$F$21,1/(1+$A10)^DCF!$B$22:$F$22)+DCF!$F$10*(1+B$8)*(1-B$8/DCF!$B$29)/($A10-B$8)/(1+$A10)^DCF!$F$22-DCF!$B$36-DCF!$B$37-DCF!$B$38+DCF!$B$39)*DCF!$B$42/DCF!$B$44) -> 580.80964 | C10: =IF(C$8>=$A10,NA(),(SUMPRODUCT(DCF!$B$14:$F$14,DCF!$B$21:$F$21,1/(1+$A10)^DCF!$B$22:$F$22)+DCF!$F$10*(1+C$8)*(1-C$8/DCF!$B$29)/($A10-C$8)/(1+$A10)^DCF!$F$22-DCF!$B$36-DCF!$B$37-DCF!$B$38+DCF!$B$39)*DCF!$B$42/DCF!$B$44) -> 573.97971 | D10: =IF(D$8>=$A10,NA(),(SUMPRODUCT(DCF!$B$14:$F$14,DCF!$B$21:$F$21,1/(1+$A10)^DCF!$B$22:$F$22)+DCF!$F$10*(1+D$8)*(1-D$8/DCF!$B$29)/($A10-D$8)/(1+$A10)^DCF!$F$22-DCF!$B$36-DCF!$B$37-DCF!$B$38+DCF!$B$39)*DCF!$B$42/DCF!$B$44) -> 565.66559 | E10: =IF(E$8>=$A10,NA(),(SUMPRODUCT(DCF!$B$14:$F$14,DCF!$B$21:$F$21,1/(1+$A10)^DCF!$B$22:$F$22)+DCF!$F$10*(1+E$8)*(1-E$8/DCF!$B$29)/($A10-E$8)/(1+$A10)^DCF!$F$22-DCF!$B$36-DCF!$B$37-DCF!$B$38+DCF!$B$39)*DCF!$B$42/DCF!$B$44) -> 555.52799 | F10: =IF(F$8>=$A10,NA(),(SUMPRODUCT(DCF!$B$14:$F$14,DCF!$B$21:$F$21,1/(1+$A10)^DCF!$B$22:$F$22)+DCF!$F$10*(1+F$8)*(1-F$8/DCF!$B$29)/($A10-F$8)/(1+$A10)^DCF!$F$22-DCF!$B$36-DCF!$B$37-DCF!$B$38+DCF!$B$39)*DCF!$B$42/DCF!$B$44) -> 543.11569
A11: =DCF!$B$27+(0)*$B$4 -> 0.1256164 | B11: =IF(B$8>=$A11,NA(),(SUMPRODUCT(DCF!$B$14:$F$14,DCF!$B$21:$F$21,1/(1+$A11)^DCF!$B$22:$F$22)+DCF!$F$10*(1+B$8)*(1-B$8/DCF!$B$29)/($A11-B$8)/(1+$A11)^DCF!$F$22-DCF!$B$36-DCF!$B$37-DCF!$B$38+DCF!$B$39)*DCF!$B$42/DCF!$B$44) -> 531.27688 | C11: =IF(C$8>=$A11,NA(),(SUMPRODUCT(DCF!$B$14:$F$14,DCF!$B$21:$F$21,1/(1+$A11)^DCF!$B$22:$F$22)+DCF!$F$10*(1+C$8)*(1-C$8/DCF!$B$29)/($A11-C$8)/(1+$A11)^DCF!$F$22-DCF!$B$36-DCF!$B$37-DCF!$B$38+DCF!$B$39)*DCF!$B$42/DCF!$B$44) -> 522.82384 | D11: =IF(D$8>=$A11,NA(),(SUMPRODUCT(DCF!$B$14:$F$14,DCF!$B$21:$F$21,1/(1+$A11)^DCF!$B$22:$F$22)+DCF!$F$10*(1+D$8)*(1-D$8/DCF!$B$29)/($A11-D$8)/(1+$A11)^DCF!$F$22-DCF!$B$36-DCF!$B$37-DCF!$B$38+DCF!$B$39)*DCF!$B$42/DCF!$B$44) -> 512.77969 | E11: =IF(E$8>=$A11,NA(),(SUMPRODUCT(DCF!$B$14:$F$14,DCF!$B$21:$F$21,1/(1+$A11)^DCF!$B$22:$F$22)+DCF!$F$10*(1+E$8)*(1-E$8/DCF!$B$29)/($A11-E$8)/(1+$A11)^DCF!$F$22-DCF!$B$36-DCF!$B$37-DCF!$B$38+DCF!$B$39)*DCF!$B$42/DCF!$B$44) -> 500.80643 | F11: =IF(F$8>=$A11,NA(),(SUMPRODUCT(DCF!$B$14:$F$14,DCF!$B$21:$F$21,1/(1+$A11)^DCF!$B$22:$F$22)+DCF!$F$10*(1+F$8)*(1-F$8/DCF!$B$29)/($A11-F$8)/(1+$A11)^DCF!$F$22-DCF!$B$36-DCF!$B$37-DCF!$B$38+DCF!$B$39)*DCF!$B$42/DCF!$B$44) -> 486.46308
A12: =DCF!$B$27+(1)*$B$4 -> 0.1306164 | B12: =IF(B$8>=$A12,NA(),(SUMPRODUCT(DCF!$B$14:$F$14,DCF!$B$21:$F$21,1/(1+$A12)^DCF!$B$22:$F$22)+DCF!$F$10*(1+B$8)*(1-B$8/DCF!$B$29)/($A12-B$8)/(1+$A12)^DCF!$F$22-DCF!$B$36-DCF!$B$37-DCF!$B$38+DCF!$B$39)*DCF!$B$42/DCF!$B$44) -> 487.25766 | C12: =IF(C$8>=$A12,NA(),(SUMPRODUCT(DCF!$B$14:$F$14,DCF!$B$21:$F$21,1/(1+$A12)^DCF!$B$22:$F$22)+DCF!$F$10*(1+C$8)*(1-C$8/DCF!$B$29)/($A12-C$8)/(1+$A12)^DCF!$F$22-DCF!$B$36-DCF!$B$37-DCF!$B$38+DCF!$B$39)*DCF!$B$42/DCF!$B$44) -> 477.67046 | D12: =IF(D$8>=$A12,NA(),(SUMPRODUCT(DCF!$B$14:$F$14,DCF!$B$21:$F$21,1/(1+$A12)^DCF!$B$22:$F$22)+DCF!$F$10*(1+D$8)*(1-D$8/DCF!$B$29)/($A12-D$8)/(1+$A12)^DCF!$F$22-DCF!$B$36-DCF!$B$37-DCF!$B$38+DCF!$B$39)*DCF!$B$42/DCF!$B$44) -> 466.4589 | E12: =IF(E$8>=$A12,NA(),(SUMPRODUCT(DCF!$B$14:$F$14,DCF!$B$21:$F$21,1/(1+$A12)^DCF!$B$22:$F$22)+DCF!$F$10*(1+E$8)*(1-E$8/DCF!$B$29)/($A12-E$8)/(1+$A12)^DCF!$F$22-DCF!$B$36-DCF!$B$37-DCF!$B$38+DCF!$B$39)*DCF!$B$42/DCF!$B$44) -> 453.30076 | F12: =IF(F$8>=$A12,NA(),(SUMPRODUCT(DCF!$B$14:$F$14,DCF!$B$21:$F$21,1/(1+$A12)^DCF!$B$22:$F$22)+DCF!$F$10*(1+F$8)*(1-F$8/DCF!$B$29)/($A12-F$8)/(1+$A12)^DCF!$F$22-DCF!$B$36-DCF!$B$37-DCF!$B$38+DCF!$B$39)*DCF!$B$42/DCF!$B$44) -> 437.78255
A13: =DCF!$B$27+(2)*$B$4 -> 0.1356164 | B13: =IF(B$8>=$A13,NA(),(SUMPRODUCT(DCF!$B$14:$F$14,DCF!$B$21:$F$21,1/(1+$A13)^DCF!$B$22:$F$22)+DCF!$F$10*(1+B$8)*(1-B$8/DCF!$B$29)/($A13-B$8)/(1+$A13)^DCF!$F$22-DCF!$B$36-DCF!$B$37-DCF!$B$38+DCF!$B$39)*DCF!$B$42/DCF!$B$44) -> 447.88599 | C13: =IF(C$8>=$A13,NA(),(SUMPRODUCT(DCF!$B$14:$F$14,DCF!$B$21:$F$21,1/(1+$A13)^DCF!$B$22:$F$22)+DCF!$F$10*(1+C$8)*(1-C$8/DCF!$B$29)/($A13-C$8)/(1+$A13)^DCF!$F$22-DCF!$B$36-DCF!$B$37-DCF!$B$38+DCF!$B$39)*DCF!$B$42/DCF!$B$44) -> 437.52544 | D13: =IF(D$8>=$A13,NA(),(SUMPRODUCT(DCF!$B$14:$F$14,DCF!$B$21:$F$21,1/(1+$A13)^DCF!$B$22:$F$22)+DCF!$F$10*(1+D$8)*(1-D$8/DCF!$B$29)/($A13-D$8)/(1+$A13)^DCF!$F$22-DCF!$B$36-DCF!$B$37-DCF!$B$38+DCF!$B$39)*DCF!$B$42/DCF!$B$44) -> 425.55312 | E13: =IF(E$8>=$A13,NA(),(SUMPRODUCT(DCF!$B$14:$F$14,DCF!$B$21:$F$21,1/(1+$A13)^DCF!$B$22:$F$22)+DCF!$F$10*(1+E$8)*(1-E$8/DCF!$B$29)/($A13-E$8)/(1+$A13)^DCF!$F$22-DCF!$B$36-DCF!$B$37-DCF!$B$38+DCF!$B$39)*DCF!$B$42/DCF!$B$44) -> 411.66913 | F13: =IF(F$8>=$A13,NA(),(SUMPRODUCT(DCF!$B$14:$F$14,DCF!$B$21:$F$21,1/(1+$A13)^DCF!$B$22:$F$22)+DCF!$F$10*(1+F$8)*(1-F$8/DCF!$B$29)/($A13-F$8)/(1+$A13)^DCF!$F$22-DCF!$B$36-DCF!$B$37-DCF!$B$38+DCF!$B$39)*DCF!$B$42/DCF!$B$44) -> 395.49425
A15: WACC x exit multiple (value per share at exit)
A16: WACC ↓ / exit EV/EBITDA → | B16: =DCF!$B$65+(-2)*$B$5 -> 6 | C16: =DCF!$B$65+(-1)*$B$5 -> 8 | D16: =DCF!$B$65+(0)*$B$5 -> 10 | E16: =DCF!$B$65+(1)*$B$5 -> 12 | F16: =DCF!$B$65+(2)*$B$5 -> 14
A17: =DCF!$B$27+(-2)*$B$4 -> 0.1156164 | B17: =(SUMPRODUCT(DCF!$B$14:$F$14,DCF!$B$21:$F$21,1/(1+$A17)^DCF!$B$22:$F$22)+B$16*DCF!$B$63/(1+$A17)^DCF!$F$22-DCF!$B$36-DCF!$B$37-DCF!$B$38+DCF!$B$39)*DCF!$B$42/DCF!$B$44 -> 706.9538 | C17: =(SUMPRODUCT(DCF!$B$14:$F$14,DCF!$B$21:$F$21,1/(1+$A17)^DCF!$B$22:$F$22)+C$16*DCF!$B$63/(1+$A17)^DCF!$F$22-DCF!$B$36-DCF!$B$37-DCF!$B$38+DCF!$B$39)*DCF!$B$42/DCF!$B$44 -> 952.29849 | D17: =(SUMPRODUCT(DCF!$B$14:$F$14,DCF!$B$21:$F$21,1/(1+$A17)^DCF!$B$22:$F$22)+D$16*DCF!$B$63/(1+$A17)^DCF!$F$22-DCF!$B$36-DCF!$B$37-DCF!$B$38+DCF!$B$39)*DCF!$B$42/DCF!$B$44 -> 1197.6432 | E17: =(SUMPRODUCT(DCF!$B$14:$F$14,DCF!$B$21:$F$21,1/(1+$A17)^DCF!$B$22:$F$22)+E$16*DCF!$B$63/(1+$A17)^DCF!$F$22-DCF!$B$36-DCF!$B$37-DCF!$B$38+DCF!$B$39)*DCF!$B$42/DCF!$B$44 -> 1442.9879 | F17: =(SUMPRODUCT(DCF!$B$14:$F$14,DCF!$B$21:$F$21,1/(1+$A17)^DCF!$B$22:$F$22)+F$16*DCF!$B$63/(1+$A17)^DCF!$F$22-DCF!$B$36-DCF!$B$37-DCF!$B$38+DCF!$B$39)*DCF!$B$42/DCF!$B$44 -> 1688.3326
A18: =DCF!$B$27+(-1)*$B$4 -> 0.1206164 | B18: =(SUMPRODUCT(DCF!$B$14:$F$14,DCF!$B$21:$F$21,1/(1+$A18)^DCF!$B$22:$F$22)+B$16*DCF!$B$63/(1+$A18)^DCF!$F$22-DCF!$B$36-DCF!$B$37-DCF!$B$38+DCF!$B$39)*DCF!$B$42/DCF!$B$44 -> 689.90385 | C18: =(SUMPRODUCT(DCF!$B$14:$F$14,DCF!$B$21:$F$21,1/(1+$A18)^DCF!$B$22:$F$22)+C$16*DCF!$B$63/(1+$A18)^DCF!$F$22-DCF!$B$36-DCF!$B$37-DCF!$B$38+DCF!$B$39)*DCF!$B$42/DCF!$B$44 -> 930.36151 | D18: =(SUMPRODUCT(DCF!$B$14:$F$14,DCF!$B$21:$F$21,1/(1+$A18)^DCF!$B$22:$F$22)+D$16*DCF!$B$63/(1+$A18)^DCF!$F$22-DCF!$B$36-DCF!$B$37-DCF!$B$38+DCF!$B$39)*DCF!$B$42/DCF!$B$44 -> 1170.8192 | E18: =(SUMPRODUCT(DCF!$B$14:$F$14,DCF!$B$21:$F$21,1/(1+$A18)^DCF!$B$22:$F$22)+E$16*DCF!$B$63/(1+$A18)^DCF!$F$22-DCF!$B$36-DCF!$B$37-DCF!$B$38+DCF!$B$39)*DCF!$B$42/DCF!$B$44 -> 1411.2768 | F18: =(SUMPRODUCT(DCF!$B$14:$F$14,DCF!$B$21:$F$21,1/(1+$A18)^DCF!$B$22:$F$22)+F$16*DCF!$B$63/(1+$A18)^DCF!$F$22-DCF!$B$36-DCF!$B$37-DCF!$B$38+DCF!$B$39)*DCF!$B$42/DCF!$B$44 -> 1651.7345
A19: =DCF!$B$27+(0)*$B$4 -> 0.1256164 | B19: =(SUMPRODUCT(DCF!$B$14:$F$14,DCF!$B$21:$F$21,1/(1+$A19)^DCF!$B$22:$F$22)+B$16*DCF!$B$63/(1+$A19)^DCF!$F$22-DCF!$B$36-DCF!$B$37-DCF!$B$38+DCF!$B$39)*DCF!$B$42/DCF!$B$44 -> 673.25559 | C19: =(SUMPRODUCT(DCF!$B$14:$F$14,DCF!$B$21:$F$21,1/(1+$A19)^DCF!$B$22:$F$22)+C$16*DCF!$B$63/(1+$A19)^DCF!$F$22-DCF!$B$36-DCF!$B$37-DCF!$B$38+DCF!$B$39)*DCF!$B$42/DCF!$B$44 -> 908.94468 | D19: =(SUMPRODUCT(DCF!$B$14:$F$14,DCF!$B$21:$F$21,1/(1+$A19)^DCF!$B$22:$F$22)+D$16*DCF!$B$63/(1+$A19)^DCF!$F$22-DCF!$B$36-DCF!$B$37-DCF!$B$38+DCF!$B$39)*DCF!$B$42/DCF!$B$44 -> 1144.6338 | E19: =(SUMPRODUCT(DCF!$B$14:$F$14,DCF!$B$21:$F$21,1/(1+$A19)^DCF!$B$22:$F$22)+E$16*DCF!$B$63/(1+$A19)^DCF!$F$22-DCF!$B$36-DCF!$B$37-DCF!$B$38+DCF!$B$39)*DCF!$B$42/DCF!$B$44 -> 1380.3228 | F19: =(SUMPRODUCT(DCF!$B$14:$F$14,DCF!$B$21:$F$21,1/(1+$A19)^DCF!$B$22:$F$22)+F$16*DCF!$B$63/(1+$A19)^DCF!$F$22-DCF!$B$36-DCF!$B$37-DCF!$B$38+DCF!$B$39)*DCF!$B$42/DCF!$B$44 -> 1616.0119
A20: =DCF!$B$27+(1)*$B$4 -> 0.1306164 | B20: =(SUMPRODUCT(DCF!$B$14:$F$14,DCF!$B$21:$F$21,1/(1+$A20)^DCF!$B$22:$F$22)+B$16*DCF!$B$63/(1+$A20)^DCF!$F$22-DCF!$B$36-DCF!$B$37-DCF!$B$38+DCF!$B$39)*DCF!$B$42/DCF!$B$44 -> 656.99774 | C20: =(SUMPRODUCT(DCF!$B$14:$F$14,DCF!$B$21:$F$21,1/(1+$A20)^DCF!$B$22:$F$22)+C$16*DCF!$B$63/(1+$A20)^DCF!$F$22-DCF!$B$36-DCF!$B$37-DCF!$B$38+DCF!$B$39)*DCF!$B$42/DCF!$B$44 -> 888.03333 | D20: =(SUMPRODUCT(DCF!$B$14:$F$14,DCF!$B$21:$F$21,1/(1+$A20)^DCF!$B$22:$F$22)+D$16*DCF!$B$63/(1+$A20)^DCF!$F$22-DCF!$B$36-DCF!$B$37-DCF!$B$38+DCF!$B$39)*DCF!$B$42/DCF!$B$44 -> 1119.0689 | E20: =(SUMPRODUCT(DCF!$B$14:$F$14,DCF!$B$21:$F$21,1/(1+$A20)^DCF!$B$22:$F$22)+E$16*DCF!$B$63/(1+$A20)^DCF!$F$22-DCF!$B$36-DCF!$B$37-DCF!$B$38+DCF!$B$39)*DCF!$B$42/DCF!$B$44 -> 1350.1045 | F20: =(SUMPRODUCT(DCF!$B$14:$F$14,DCF!$B$21:$F$21,1/(1+$A20)^DCF!$B$22:$F$22)+F$16*DCF!$B$63/(1+$A20)^DCF!$F$22-DCF!$B$36-DCF!$B$37-DCF!$B$38+DCF!$B$39)*DCF!$B$42/DCF!$B$44 -> 1581.1401
A21: =DCF!$B$27+(2)*$B$4 -> 0.1356164 | B21: =(SUMPRODUCT(DCF!$B$14:$F$14,DCF!$B$21:$F$21,1/(1+$A21)^DCF!$B$22:$F$22)+B$16*DCF!$B$63/(1+$A21)^DCF!$F$22-DCF!$B$36-DCF!$B$37-DCF!$B$38+DCF!$B$39)*DCF!$B$42/DCF!$B$44 -> 641.11937 | C21: =(SUMPRODUCT(DCF!$B$14:$F$14,DCF!$B$21:$F$21,1/(1+$A21)^DCF!$B$22:$F$22)+C$16*DCF!$B$63/(1+$A21)^DCF!$F$22-DCF!$B$36-DCF!$B$37-DCF!$B$38+DCF!$B$39)*DCF!$B$42/DCF!$B$44 -> 867.61327 | D21: =(SUMPRODUCT(DCF!$B$14:$F$14,DCF!$B$21:$F$21,1/(1+$A21)^DCF!$B$22:$F$22)+D$16*DCF!$B$63/(1+$A21)^DCF!$F$22-DCF!$B$36-DCF!$B$37-DCF!$B$38+DCF!$B$39)*DCF!$B$42/DCF!$B$44 -> 1094.1072 | E21: =(SUMPRODUCT(DCF!$B$14:$F$14,DCF!$B$21:$F$21,1/(1+$A21)^DCF!$B$22:$F$22)+E$16*DCF!$B$63/(1+$A21)^DCF!$F$22-DCF!$B$36-DCF!$B$37-DCF!$B$38+DCF!$B$39)*DCF!$B$42/DCF!$B$44 -> 1320.6011 | F21: =(SUMPRODUCT(DCF!$B$14:$F$14,DCF!$B$21:$F$21,1/(1+$A21)^DCF!$B$22:$F$22)+F$16*DCF!$B$63/(1+$A21)^DCF!$F$22-DCF!$B$36-DCF!$B$37-DCF!$B$38+DCF!$B$39)*DCF!$B$42/DCF!$B$44 -> 1547.095

Sheet Checks
A1: Adani Ports and Special Economic Zone Ltd - Checks
A2: INR cr unless stated | built 2026-10-14 | blue = input, black = formula, green = link to another sheet
A4: Actuals | B4: Mar-17 | C4: Mar-18 | D4: Mar-19 | E4: Mar-20 | F4: Mar-21 | G4: Mar-22 | H4: Mar-23 | I4: Mar-24 | J4: Mar-25 | K4: Mar-26 | L4: Mar-27E | M4: Mar-28E | N4: Mar-29E | O4: Mar-30E | P4: Mar-31E
A5: Integrity checks - every one of these must read zero
A6: Total assets less total liabilities and equity | B6: =('Balance Sheet'!B13-'Balance Sheet'!B22) -> 0 | C6: =('Balance Sheet'!C13-'Balance Sheet'!C22) -> 0 | D6: =('Balance Sheet'!D13-'Balance Sheet'!D22) -> 0 | E6: =('Balance Sheet'!E13-'Balance Sheet'!E22) -> 0 | F6: =('Balance Sheet'!F13-'Balance Sheet'!F22) -> 0 | G6: =('Balance Sheet'!G13-'Balance Sheet'!G22) -> 0 | H6: =('Balance Sheet'!H13-'Balance Sheet'!H22) -> 0 | I6: =('Balance Sheet'!I13-'Balance Sheet'!I22) -> 0 | ... P6: =('Balance Sheet'!P13-'Balance Sheet'!P22) -> 0
A7: Balance sheet cash less cash flow closing cash | B7: =('Balance Sheet'!B6-'Cash Flow'!B23) -> -8330.01 | C7: =('Balance Sheet'!C6-'Cash Flow'!C23) -> 117.54 | D7: =('Balance Sheet'!D6-'Cash Flow'!D23) -> -479.43 | E7: =('Balance Sheet'!E6-'Cash Flow'!E23) -> -2028.33 | F7: =('Balance Sheet'!F6-'Cash Flow'!F23) -> 1006.35 | G7: =('Balance Sheet'!G6-'Cash Flow'!G23) -> 7550.11 | H7: =('Balance Sheet'!H6-'Cash Flow'!H23) -> -661.07 | I7: =('Balance Sheet'!I6-'Cash Flow'!I23) -> 574.3 | ... P7: =('Balance Sheet'!P6-'Cash Flow'!P23) -> 0
A8: Reserves roll-forward residual | B8: =('Balance Sheet'!B16-(((0+'Income Statement'!B18)-Schedules!B22)+Drivers!B27)) -> 13469.49 | C8: =('Balance Sheet'!C16-((('Balance Sheet'!B16+'Income Statement'!C18)-Schedules!C22)+Drivers!C27)) -> 117.54 | D8: =('Balance Sheet'!D16-((('Balance Sheet'!C16+'Income Statement'!D18)-Schedules!D22)+Drivers!D27)) -> -479.43 | E8: =('Balance Sheet'!E16-((('Balance Sheet'!D16+'Income Statement'!E18)-Schedules!E22)+Drivers!E27)) -> -2020.49 | F8: =('Balance Sheet'!F16-((('Balance Sheet'!E16+'Income Statement'!F18)-Schedules!F22)+Drivers!F27)) -> 1006.35 | G8: =('Balance Sheet'!G16-((('Balance Sheet'!F16+'Income Statement'!G18)-Schedules!G22)+Drivers!G27)) -> 7533.99 | H8: =('Balance Sheet'!H16-((('Balance Sheet'!G16+'Income Statement'!H18)-Schedules!H22)+Drivers!H27)) -> -670.63 | I8: =('Balance Sheet'!I16-((('Balance Sheet'!H16+'Income Statement'!I18)-Schedules!I22)+Drivers!I27)) -> 574.3 | J8: =('Balance Sheet'!J16-((('Balance Sheet'!I16+'Income Statement'!J18)-Schedules!J22)+Drivers!J27)) -> -89.59 | ... P8: =('Balance Sheet'!P16-((('Balance Sheet'!O16+'Income Statement'!P18)-Schedules!P22)+Drivers!P27)) -> 0
A9: Net block roll-forward residual | B9: =('Balance Sheet'!B10-Schedules!B9) -> 22213.69 | C9: =('Balance Sheet'!C10-Schedules!C9) -> 0 | D9: =('Balance Sheet'!D10-Schedules!D9) -> 0 | E9: =('Balance Sheet'!E10-Schedules!E9) -> 0 | F9: =('Balance Sheet'!F10-Schedules!F9) -> 0 | G9: =('Balance Sheet'!G10-Schedules!G9) -> 0 | H9: =('Balance Sheet'!H10-Schedules!H9) -> 0 | I9: =('Balance Sheet'!I10-Schedules!I9) -> 0 | ... P9: =('Balance Sheet'!P10-Schedules!P9) -> 0
A10: Sanity checks - these must not go negative
A11: Cash less the minimum cash balance | B11: =('Balance Sheet'!B6-Drivers!B29) -> 1976.8 | C11: =('Balance Sheet'!C6-Drivers!C29) -> 2967.55 | D11: =('Balance Sheet'!D6-Drivers!D29) -> 5967.3 | E11: =('Balance Sheet'!E6-Drivers!E29) -> 7313.86 | F11: =('Balance Sheet'!F6-Drivers!F29) -> 4700.78 | G11: =('Balance Sheet'!G6-Drivers!G29) -> 10667.41 | H11: =('Balance Sheet'!H6-Drivers!H29) -> 4334.31 | I11: =('Balance Sheet'!I6-Drivers!I29) -> 7631.88 | ... P11: =('Balance Sheet'!P6-Drivers!P29) -> 49620.609
A12: Revolver balance | B12: ='Balance Sheet'!B18 -> 0 | C12: ='Balance Sheet'!C18 -> 0 | D12: ='Balance Sheet'!D18 -> 0 | E12: ='Balance Sheet'!E18 -> 0 | F12: ='Balance Sheet'!F18 -> 0 | G12: ='Balance Sheet'!G18 -> 0 | H12: ='Balance Sheet'!H18 -> 0 | I12: ='Balance Sheet'!I18 -> 0 | ... P12: ='Balance Sheet'!P18 -> 0
A13: Net block | B13: ='Balance Sheet'!B10 -> 21053.5 | C13: ='Balance Sheet'!C10 -> 22670.01 | D13: ='Balance Sheet'!D10 -> 28121.42 | E13: ='Balance Sheet'!E10 -> 32714.51 | F13: ='Balance Sheet'!F10 -> 48290.96 | G13: ='Balance Sheet'!G10 -> 62552.92 | H13: ='Balance Sheet'!H10 -> 72223.73 | I13: ='Balance Sheet'!I10 -> 75147.81 | ... P13: ='Balance Sheet'!P10 -> 176959.62
A14: Shareholders' equity | B14: =Schedules!B24 -> 17525.98 | C14: =Schedules!C24 -> 20902.95 | D14: =Schedules!D24 -> 24372.32 | E14: =Schedules!E24 -> 25456.96 | F14: =Schedules!F24 -> 30441.73 | G14: =Schedules!G24 -> 41821.69 | H14: =Schedules!H24 -> 45389.39 | I14: =Schedules!I24 -> 52778.24 | ... P14: =Schedules!P24 -> 178972.79
